{
  "info": {
    "id": 1891,
    "title": "Track 8",
    "category": "한국 대중 음악",
    "sub_category": "발라드",
    "year": "2008",
    "month": "12",
    "time": "3:00",
    "beat": "4/4",
    "tempo": "72",
    "sec": "3.3",
    "original_key": "A",
    "singer": "이소라",
    "created_at": "2021-02-15 22:12:14"
  },
  "musics": [
    {
      "id": 45796,
      "sort": 1,
      "chord_1": " ",
      "chord_2": "",
      "chord_3": "",
      "chord_4": "",
      "chord_5": " ",
      "chord_6": "",
      "chord_7": "",
      "chord_8": "",
      "chord_9": " ",
      "chord_10": "",
      "chord_11": "",
      "chord_12": "",
      "chord_13": "A",
      "chord_14": "",
      "chord_15": "",
      "chord_16": "",
      "lyrics_1": null,
      "lyrics_2": null,
      "lyrics_3": null,
      "lyrics_4": null,
      "created_at": "2021-02-15 22:12:14"
    },
    {
      "id": 45797,
      "sort": 2,
      "chord_1": "A",
      "chord_2": "",
      "chord_3": "",
      "chord_4": "",
      "chord_5": "",
      "chord_6": "",
      "chord_7": "",
      "chord_8": "",
      "chord_9": "",
      "chord_10": "",
      "chord_11": "",
      "chord_12": "",
      "chord_13": "F<sup>#</sup>m",
      "chord_14": "",
      "chord_15": "",
      "chord_16": "",
      "lyrics_1": null,
      "lyrics_2": "죽은   그  - 가   부   - 르   는  - 노   래",
      "lyrics_3": "-",
      "lyrics_4": "술에   취  - 해   말  - 하   는   - 노",
      "created_at": "2021-02-15 22:12:14"
    },
    {
      "id": 45798,
      "sort": 3,
      "chord_1": "F<sup>#</sup>m",
      "chord_2": "",
      "chord_3": "",
      "chord_4": "",
      "chord_5": "D",
      "chord_6": "",
      "chord_7": "",
      "chord_8": "",
      "chord_9": "E",
      "chord_10": "",
      "chord_11": "",
      "chord_12": "",
      "chord_13": "A",
      "chord_14": "",
      "chord_15": "",
      "chord_16": "",
      "lyrics_1": " - 래                    간   절    히   원",
      "lyrics_2": " -    해                       wan - na stay",
      "lyrics_3": "with   you                        oh",
      "lyrics_4": " -      to -   night",
      "created_at": "2021-02-15 22:12:14"
    },
    {
      "id": 45799,
      "sort": 4,
      "chord_1": "A",
      "chord_2": "",
      "chord_3": "",
      "chord_4": "",
      "chord_5": "",
      "chord_6": "",
      "chord_7": "",
      "chord_8": "",
      "chord_9": "",
      "chord_10": "",
      "chord_11": "",
      "chord_12": "",
      "chord_13": "F<sup>#</sup>m",
      "chord_14": "",
      "chord_15": "",
      "chord_16": "",
      "lyrics_1": null,
      "lyrics_2": "죽은   그  - 가   부   - 르   는  - 노   래",
      "lyrics_3": " -                                        지난이",
      "lyrics_4": " - 별   이  - 슬   프  - 게   생   - 각   나",
      "created_at": "2021-02-15 22:12:14"
    },
    {
      "id": 45800,
      "sort": 5,
      "chord_1": "F<sup>#</sup>m",
      "chord_2": "",
      "chord_3": "",
      "chord_4": "",
      "chord_5": "D",
      "chord_6": "",
      "chord_7": "",
      "chord_8": "",
      "chord_9": "E",
      "chord_10": "",
      "chord_11": "",
      "chord_12": "",
      "chord_13": "A",
      "chord_14": "",
      "chord_15": "",
      "chord_16": "",
      "lyrics_1": " -  -        -            간   절    히  원",
      "lyrics_2": " -    해                       wan - na stay",
      "lyrics_3": "with   you                        oh",
      "lyrics_4": " -      to -   night",
      "created_at": "2021-02-15 22:12:14"
    },
    {
      "id": 45801,
      "sort": 6,
      "chord_1": "A",
      "chord_2": "",
      "chord_3": "",
      "chord_4": "",
      "chord_5": "Bm7",
      "chord_6": "",
      "chord_7": "",
      "chord_8": "",
      "chord_9": "E7",
      "chord_10": "",
      "chord_11": "",
      "chord_12": "",
      "chord_13": "C<sup>#</sup>m7",
      "chord_14": "",
      "chord_15": "",
      "chord_16": "",
      "lyrics_1": " -                 꼭    그   래    야   할",
      "lyrics_2": "일    -     이   었     -    을          까",
      "lyrics_3": " -                 꼭    겪   어    야   할",
      "lyrics_4": "일   이          었     -     을          까",
      "created_at": "2021-02-15 22:12:14"
    },
    {
      "id": 45802,
      "sort": 7,
      "chord_1": "F<sup>#</sup>m7",
      "chord_2": "",
      "chord_3": "",
      "chord_4": "",
      "chord_5": "Bm7",
      "chord_6": "",
      "chord_7": "",
      "chord_8": "",
      "chord_9": "E7sus4",
      "chord_10": "",
      "chord_11": "",
      "chord_12": "",
      "chord_13": "A",
      "chord_14": "",
      "chord_15": "",
      "chord_16": "",
      "lyrics_1": " -                 혼    자   서    남    -",
      "lyrics_2": "겨           -    진방  -                 그",
      "lyrics_3": " -                 마     -    지    막 -",
      "lyrics_4": " -    끝     -",
      "created_at": "2021-02-15 22:12:14"
    },
    {
      "id": 45803,
      "sort": 8,
      "chord_1": "A",
      "chord_2": "",
      "chord_3": "",
      "chord_4": "",
      "chord_5": "Bm7",
      "chord_6": "",
      "chord_7": "",
      "chord_8": "",
      "chord_9": "E7",
      "chord_10": "",
      "chord_11": "",
      "chord_12": "",
      "chord_13": "C<sup>#</sup>m7",
      "chord_14": "",
      "chord_15": "",
      "chord_16": "",
      "lyrics_1": " -                 꼭    그   래    야   할",
      "lyrics_2": "일    -     이   었     -    을          까",
      "lyrics_3": " -                 꼭    떠   나    야   할",
      "lyrics_4": "일   이          었     -     을          까",
      "created_at": "2021-02-15 22:12:14"
    },
    {
      "id": 45804,
      "sort": 9,
      "chord_1": "F<sup>#</sup>m7",
      "chord_2": "",
      "chord_3": "",
      "chord_4": "",
      "chord_5": "Bm7",
      "chord_6": "",
      "chord_7": "",
      "chord_8": "",
      "chord_9": "E7sus4",
      "chord_10": "",
      "chord_11": "",
      "chord_12": "",
      "chord_13": "A",
      "chord_14": "",
      "chord_15": "",
      "chord_16": "",
      "lyrics_1": " -                 먼    저   사    라     -",
      "lyrics_2": "진           -    그대   -                또",
      "lyrics_3": " -    올     -    수가   -               없",
      "lyrics_4": " -    네     -",
      "created_at": "2021-02-15 22:12:14"
    },
    {
      "id": 45805,
      "sort": 10,
      "chord_1": "A",
      "chord_2": "",
      "chord_3": "",
      "chord_4": "",
      "chord_5": "",
      "chord_6": "",
      "chord_7": "",
      "chord_8": "",
      "chord_9": "",
      "chord_10": "",
      "chord_11": "",
      "chord_12": "",
      "chord_13": "F<sup>#</sup>m",
      "chord_14": "",
      "chord_15": "",
      "chord_16": "",
      "lyrics_1": " -",
      "lyrics_2": "죽은   그  - 가   부   - 르   는  - 노   래",
      "lyrics_3": "-",
      "lyrics_4": "술에   취  - 해   말  - 하   는   - 노",
      "created_at": "2021-02-15 22:12:14"
    },
    {
      "id": 45806,
      "sort": 11,
      "chord_1": "F<sup>#</sup>m",
      "chord_2": "",
      "chord_3": "",
      "chord_4": "",
      "chord_5": "D",
      "chord_6": "",
      "chord_7": "",
      "chord_8": "",
      "chord_9": "E7",
      "chord_10": "",
      "chord_11": "",
      "chord_12": "",
      "chord_13": "A",
      "chord_14": "",
      "chord_15": "",
      "chord_16": "",
      "lyrics_1": " - 래                    간   절    히   원",
      "lyrics_2": " -    해                       wan - na stay",
      "lyrics_3": "with   you                          I      wan  na",
      "lyrics_4": "be                   be                     with    -",
      "created_at": "2021-02-15 22:12:14"
    },
    {
      "id": 45807,
      "sort": 12,
      "chord_1": "A",
      "chord_2": "",
      "chord_3": "",
      "chord_4": "",
      "chord_5": "",
      "chord_6": "",
      "chord_7": "",
      "chord_8": "",
      "chord_9": "",
      "chord_10": "",
      "chord_11": "",
      "chord_12": "",
      "chord_13": "F<sup>#</sup>m",
      "chord_14": "",
      "chord_15": "",
      "chord_16": "",
      "lyrics_1": "you",
      "lyrics_2": null,
      "lyrics_3": null,
      "lyrics_4": null,
      "created_at": "2021-02-15 22:12:14"
    },
    {
      "id": 45808,
      "sort": 13,
      "chord_1": "F<sup>#</sup>m",
      "chord_2": "",
      "chord_3": "",
      "chord_4": "",
      "chord_5": "D",
      "chord_6": "",
      "chord_7": "",
      "chord_8": "",
      "chord_9": "E7",
      "chord_10": "",
      "chord_11": "",
      "chord_12": "",
      "chord_13": "A",
      "chord_14": "",
      "chord_15": "",
      "chord_16": "",
      "lyrics_1": null,
      "lyrics_2": null,
      "lyrics_3": null,
      "lyrics_4": null,
      "created_at": "2021-02-15 22:12:14"
    },
    {
      "id": 45809,
      "sort": 14,
      "chord_1": "A",
      "chord_2": "",
      "chord_3": "",
      "chord_4": "",
      "chord_5": "Bm7",
      "chord_6": "",
      "chord_7": "",
      "chord_8": "",
      "chord_9": "E7",
      "chord_10": "",
      "chord_11": "",
      "chord_12": "",
      "chord_13": "C<sup>#</sup>m7",
      "chord_14": "",
      "chord_15": "",
      "chord_16": "",
      "lyrics_1": " -                        그   래    야   할",
      "lyrics_2": "일    -     이   었     -    을          까",
      "lyrics_3": " -                 꼭    겪   어    야   할",
      "lyrics_4": "일   이          었     -     을          까",
      "created_at": "2021-02-15 22:12:14"
    },
    {
      "id": 45810,
      "sort": 15,
      "chord_1": "F<sup>#</sup>m7",
      "chord_2": "",
      "chord_3": "",
      "chord_4": "",
      "chord_5": "Bm7",
      "chord_6": "",
      "chord_7": "",
      "chord_8": "",
      "chord_9": "E7sus4",
      "chord_10": "",
      "chord_11": "",
      "chord_12": "",
      "chord_13": "A",
      "chord_14": "",
      "chord_15": "",
      "chord_16": "",
      "lyrics_1": " -                 혼    자   서    남    -",
      "lyrics_2": "겨           -    진방  -                 그",
      "lyrics_3": " -                 마     -    지    막 -",
      "lyrics_4": " -    끝     -",
      "created_at": "2021-02-15 22:12:14"
    },
    {
      "id": 45811,
      "sort": 16,
      "chord_1": "A",
      "chord_2": "",
      "chord_3": "",
      "chord_4": "",
      "chord_5": "Bm7",
      "chord_6": "",
      "chord_7": "",
      "chord_8": "",
      "chord_9": "E7",
      "chord_10": "",
      "chord_11": "",
      "chord_12": "",
      "chord_13": "C<sup>#</sup>m7",
      "chord_14": "",
      "chord_15": "",
      "chord_16": "",
      "lyrics_1": " -                 꼭    그   래    야   할",
      "lyrics_2": "일    -     이   었     -    을          까",
      "lyrics_3": " -                 꼭    떠   나    야   할",
      "lyrics_4": "일   이          었     -     을          까",
      "created_at": "2021-02-15 22:12:14"
    },
    {
      "id": 45812,
      "sort": 17,
      "chord_1": "F<sup>#</sup>m7",
      "chord_2": "",
      "chord_3": "",
      "chord_4": "",
      "chord_5": "Bm7",
      "chord_6": "",
      "chord_7": "",
      "chord_8": "",
      "chord_9": "E7sus4",
      "chord_10": "",
      "chord_11": "",
      "chord_12": "",
      "chord_13": "A",
      "chord_14": "",
      "chord_15": "",
      "chord_16": "",
      "lyrics_1": " -                 먼    저   사    라     -",
      "lyrics_2": "진           -    그대  -                 또",
      "lyrics_3": " -    올     -    수가  -                없",
      "lyrics_4": " -    네     -      (볼  -    수    도   없",
      "created_at": "2021-02-15 22:12:14"
    },
    {
      "id": 45813,
      "sort": 18,
      "chord_1": "A",
      "chord_2": "",
      "chord_3": "",
      "chord_4": "",
      "chord_5": "D",
      "chord_6": "",
      "chord_7": "",
      "chord_8": "",
      "chord_9": "A",
      "chord_10": "",
      "chord_11": "E7/G<sup>#</sup>",
      "chord_12": "",
      "chord_13": "F<sup>#</sup>m",
      "chord_14": "",
      "chord_15": "",
      "chord_16": "",
      "lyrics_1": " -    어     - )                            oh -",
      "lyrics_2": " -                    죽  -    음    보   다",
      "lyrics_3": "내          가   남     -     긴         전",
      "lyrics_4": " -    부          를     -    기          억",
      "created_at": "2021-02-15 22:12:14"
    },
    {
      "id": 45814,
      "sort": 19,
      "chord_1": "D",
      "chord_2": "",
      "chord_3": "",
      "chord_4": "",
      "chord_5": "E7sus4",
      "chord_6": "",
      "chord_7": "",
      "chord_8": "",
      "chord_9": "E7",
      "chord_10": "",
      "chord_11": "",
      "chord_12": "",
      "chord_13": "A",
      "chord_14": "",
      "chord_15": "",
      "chord_16": "",
      "lyrics_1": " -    할    께",
      "lyrics_2": " -",
      "lyrics_3": null,
      "lyrics_4": "죽은   그  - 가   부   - 르   는  - 노   래",
      "created_at": "2021-02-15 22:12:14"
    },
    {
      "id": 45815,
      "sort": 20,
      "chord_1": "A",
      "chord_2": "",
      "chord_3": "",
      "chord_4": "",
      "chord_5": "F<sup>#</sup>m",
      "chord_6": "",
      "chord_7": "",
      "chord_8": "",
      "chord_9": "",
      "chord_10": "",
      "chord_11": "",
      "chord_12": "",
      "chord_13": "D",
      "chord_14": "",
      "chord_15": "",
      "chord_16": "",
      "lyrics_1": " -                                        남은이",
      "lyrics_2": " - 별   이  - 슬   프  - 게   생  - 각   나",
      "lyrics_3": " -  -        -           간   절     히   원",
      "lyrics_4": " -    해                            wanna lean",
      "created_at": "2021-02-15 22:12:14"
    },
    {
      "id": 45816,
      "sort": 21,
      "chord_1": "E7",
      "chord_2": "",
      "chord_3": "",
      "chord_4": "",
      "chord_5": "A",
      "chord_6": "",
      "chord_7": "",
      "chord_8": "",
      "chord_9": " ",
      "chord_10": "",
      "chord_11": "",
      "chord_12": "",
      "chord_13": " ",
      "chord_14": "",
      "chord_15": "",
      "chord_16": "",
      "lyrics_1": "on    you                                    I  wanna",
      "lyrics_2": "be                    with   -   you",
      "lyrics_3": null,
      "lyrics_4": null,
      "created_at": "2021-02-15 22:12:14"
    }
  ]
}