{
  "info": {
    "id": 4902,
    "title": "아이와 나의 바다",
    "category": "한국 대중 음악",
    "sub_category": "발라드",
    "year": "2021",
    "month": "3",
    "time": "3:00",
    "beat": "4/4",
    "tempo": "67",
    "sec": "3.6",
    "original_key": "E",
    "singer": "아이유 (IU)",
    "created_at": "2021-04-13 14:36:35"
  },
  "musics": [
    {
      "id": 114440,
      "sort": 1,
      "chord_1": "",
      "chord_2": "",
      "chord_3": "",
      "chord_4": "",
      "chord_5": "E",
      "chord_6": "",
      "chord_7": "",
      "chord_8": "",
      "chord_9": "C<sup>#</sup>m",
      "chord_10": "",
      "chord_11": "",
      "chord_12": "",
      "chord_13": "A",
      "chord_14": "",
      "chord_15": "",
      "chord_16": "",
      "lyrics_1": "                                     그러 나   ",
      "lyrics_2": " -                                   시간이 지",
      "lyrics_3": " -  - 나 도 -                       아물지 않",
      "lyrics_4": " -    는 일 - 들 이    -                 있 지",
      "created_at": "2021-04-13 14:36:35"
    },
    {
      "id": 114441,
      "sort": 2,
      "chord_1": "E",
      "chord_2": "",
      "chord_3": "",
      "chord_4": "",
      "chord_5": "A/C<sup>#</sup>",
      "chord_6": "",
      "chord_7": "B/D<sup>#</sup>",
      "chord_8": "",
      "chord_9": "E",
      "chord_10": "",
      "chord_11": "A",
      "chord_12": "",
      "chord_13": "F<sup>#</sup>m7",
      "chord_14": "",
      "chord_15": "Bsus4",
      "chord_16": "",
      "lyrics_1": " -  -                                내가 날   ",
      "lyrics_2": " -          온전 히    -                 사 랑",
      "lyrics_3": "하   지 못 - 해 서--- -                 맘 이",
      "lyrics_4": " -    가 난 -    한 밤 -          이   야   ",
      "created_at": "2021-04-13 14:36:35"
    },
    {
      "id": 114442,
      "sort": 3,
      "chord_1": "A/E",
      "chord_2": "",
      "chord_3": "E",
      "chord_4": "",
      "chord_5": "C<sup>#</sup>m",
      "chord_6": "",
      "chord_7": "",
      "chord_8": "E/G<sup>#</sup>",
      "chord_9": "A",
      "chord_10": "",
      "chord_11": "",
      "chord_12": "Bsus4",
      "chord_13": "C<sup>#</sup>m7",
      "chord_14": "",
      "chord_15": "",
      "chord_16": "E/G<sup>#</sup>",
      "lyrics_1": " -",
      "lyrics_2": "거울 속에 -             마주친 얼 - 굴    이",
      "lyrics_3": "어색 해서 -                                   ",
      "lyrics_4": "습관 처럼 -              조용히 눈 - 을    감",
      "created_at": "2021-04-13 14:36:35"
    },
    {
      "id": 114443,
      "sort": 4,
      "chord_1": "A",
      "chord_2": "",
      "chord_3": "",
      "chord_4": "",
      "chord_5": "F<sup>#</sup>m11",
      "chord_6": "",
      "chord_7": "B7sus4",
      "chord_8": "",
      "chord_9": "C<sup>#</sup>m7",
      "chord_10": "",
      "chord_11": "E",
      "chord_12": "",
      "chord_13": "D",
      "chord_14": "",
      "chord_15": "A/C<sup>#</sup>",
      "chord_16": "",
      "lyrics_1": " - 아       -                                   ",
      "lyrics_2": "밤이 되면 -             서둘러 내 - 일    로",
      "lyrics_3": "가고 싶어 -             수많은 소 - 원 아 - ",
      "lyrics_4": "래          매   일 다 -    른 꿈 - 을    꾸",
      "created_at": "2021-04-13 14:36:35"
    },
    {
      "id": 114444,
      "sort": 5,
      "chord_1": "B7sus4",
      "chord_2": "",
      "chord_3": "B",
      "chord_4": "",
      "chord_5": "E",
      "chord_6": "",
      "chord_7": "Bsus4",
      "chord_8": "",
      "chord_9": "A6",
      "chord_10": "",
      "chord_11": "",
      "chord_12": "Bsus4",
      "chord_13": "C<sup>#</sup>m7",
      "chord_14": "",
      "chord_15": "E/G<sup>#</sup>",
      "chord_16": "",
      "lyrics_1": " - 던       -                       아이 는   ",
      "lyrics_2": " -          그렇 게    -       오 랜시 간   ",
      "lyrics_3": " -                                   겨우 내가",
      "lyrics_4": " -    되 려 - 고    아 -    팠 던 - 걸 까   ",
      "created_at": "2021-04-13 14:36:35"
    },
    {
      "id": 114445,
      "sort": 6,
      "chord_1": "A",
      "chord_2": "",
      "chord_3": "",
      "chord_4": "Bsus4",
      "chord_5": "E",
      "chord_6": "",
      "chord_7": "Bsus4",
      "chord_8": "B",
      "chord_9": "A",
      "chord_10": "",
      "chord_11": "",
      "chord_12": "Bsus4",
      "chord_13": "C<sup>#</sup>m7",
      "chord_14": "",
      "chord_15": "E/G<sup>#</sup>",
      "chord_16": "",
      "lyrics_1": " -                                   쌓이 는   ",
      "lyrics_2": " -       하 루만 큼    -       더 멀어 져   ",
      "lyrics_3": " -                                   우리는 화",
      "lyrics_4": " -    해 할 - 수    없 -    을 것 - 같    아",
      "created_at": "2021-04-13 14:36:35"
    },
    {
      "id": 114446,
      "sort": 7,
      "chord_1": "A",
      "chord_2": "",
      "chord_3": "",
      "chord_4": "",
      "chord_5": "D",
      "chord_6": "",
      "chord_7": "A/C<sup>#</sup>",
      "chord_8": "",
      "chord_9": "Bsus4",
      "chord_10": "",
      "chord_11": "",
      "chord_12": "",
      "chord_13": "EM7",
      "chord_14": "",
      "chord_15": "",
      "chord_16": "",
      "lyrics_1": " -  -  -                                        ",
      "lyrics_2": "나    아 지 - 지    않 -    을 것 - 같    아",
      "lyrics_3": " -                                   어린 날   ",
      "lyrics_4": " -                                    내맘엔 영",
      "created_at": "2021-04-13 14:36:35"
    },
    {
      "id": 114447,
      "sort": 8,
      "chord_1": "C<sup>#</sup>m11",
      "chord_2": "",
      "chord_3": "",
      "chord_4": "",
      "chord_5": "A",
      "chord_6": "",
      "chord_7": "",
      "chord_8": "",
      "chord_9": "EM7",
      "chord_10": "",
      "chord_11": "",
      "chord_12": "",
      "chord_13": "A/C<sup>#</sup>",
      "chord_14": "",
      "chord_15": "B/D<sup>#</sup>",
      "chord_16": "",
      "lyrics_1": " -  - 원 히 -                       가물지 않",
      "lyrics_2": " -    는 바 - 다 가    -       있 었   지   ",
      "lyrics_3": " -  -  -                             이제 는   ",
      "lyrics_4": " -                     흔 적   만 이 - 남 아   ",
      "created_at": "2021-04-13 14:36:35"
    },
    {
      "id": 114448,
      "sort": 9,
      "chord_1": "E",
      "chord_2": "",
      "chord_3": "B/A",
      "chord_4": "A",
      "chord_5": "E/B",
      "chord_6": "",
      "chord_7": "B7sus4",
      "chord_8": "",
      "chord_9": "C<sup>#</sup>m7",
      "chord_10": "",
      "chord_11": "",
      "chord_12": "",
      "chord_13": "A",
      "chord_14": "",
      "chord_15": "",
      "chord_16": "",
      "lyrics_1": " -                   희 미   한 그 -    곳 엔",
      "lyrics_2": " -           -       - - -                      ",
      "lyrics_3": "설렘 으로 -             차오 르던 - 나    의",
      "lyrics_4": "숨 소리와 -                                   ",
      "created_at": "2021-04-13 14:36:35"
    },
    {
      "id": 114449,
      "sort": 10,
      "chord_1": "C<sup>#</sup>m7",
      "chord_2": "",
      "chord_3": "",
      "chord_4": "",
      "chord_5": "A",
      "chord_6": "",
      "chord_7": "",
      "chord_8": "",
      "chord_9": "A6",
      "chord_10": "",
      "chord_11": "Bsus4",
      "chord_12": "",
      "chord_13": "C<sup>#</sup>m11",
      "chord_14": "",
      "chord_15": "EM7",
      "chord_16": "",
      "lyrics_1": "머리 위로 -           선선히 부 - 는    바",
      "lyrics_2": " -  - 람    -                                 파",
      "lyrics_3": "도가 되어 -             어디로 든 - 달    려",
      "lyrics_4": "가고 싶어 -             작은 두려 - 움 아래",
      "created_at": "2021-04-13 14:36:35"
    },
    {
      "id": 114450,
      "sort": 11,
      "chord_1": "D",
      "chord_2": "",
      "chord_3": "A/C<sup>#</sup>",
      "chord_4": "",
      "chord_5": "B7sus4",
      "chord_6": "",
      "chord_7": "",
      "chord_8": "",
      "chord_9": "E",
      "chord_10": "",
      "chord_11": "Bsus4",
      "chord_12": "",
      "chord_13": "A",
      "chord_14": "",
      "chord_15": "",
      "chord_16": "B",
      "lyrics_1": " -       천 천   히 두 -    눈 을 -    뜨 면",
      "lyrics_2": " -                                   세상 은   ",
      "lyrics_3": " -          그렇 게    -       모 든순 간   ",
      "lyrics_4": " -                                   내게로 와",
      "created_at": "2021-04-13 14:36:35"
    },
    {
      "id": 114451,
      "sort": 12,
      "chord_1": "C<sup>#</sup>m11",
      "chord_2": "",
      "chord_3": "E/G<sup>#</sup>",
      "chord_4": "",
      "chord_5": "A",
      "chord_6": "",
      "chord_7": "",
      "chord_8": "B",
      "chord_9": "E",
      "chord_10": "",
      "chord_11": "Bsus4",
      "chord_12": "",
      "chord_13": "A",
      "chord_14": "",
      "chord_15": "",
      "chord_16": "B7sus4",
      "lyrics_1": " - 눈    부 - 신    선 -    물 이 - 되 고   ",
      "lyrics_2": " -                                   숱하 게   ",
      "lyrics_3": " -       의 심하 던    -    나 는 그제 야   ",
      "lyrics_4": " -                                   나에게 대",
      "created_at": "2021-04-13 14:36:35"
    },
    {
      "id": 114452,
      "sort": 13,
      "chord_1": "C<sup>#</sup>m7",
      "chord_2": "",
      "chord_3": "EM7/G<sup>#</sup>",
      "chord_4": "",
      "chord_5": "A",
      "chord_6": "",
      "chord_7": "",
      "chord_8": "",
      "chord_9": "A/G",
      "chord_10": "",
      "chord_11": "F<sup>#</sup>m11",
      "chord_12": "",
      "chord_13": "Esus4",
      "chord_14": "",
      "chord_15": "",
      "chord_16": "F<sup>#</sup>m   E",
      "lyrics_1": " -    답 할 - 수    있 -    을 것 -    같   ",
      "lyrics_2": "아",
      "lyrics_3": " -          산   너     -    머 의 - 기    억",
      "lyrics_4": " -       이 -  -         -                      ",
      "created_at": "2021-04-13 14:36:35"
    },
    {
      "id": 114453,
      "sort": 14,
      "chord_1": "D",
      "chord_2": "",
      "chord_3": "A/C<sup>#</sup>",
      "chord_4": "C6",
      "chord_5": "E/B",
      "chord_6": "",
      "chord_7": "",
      "chord_8": "",
      "chord_9": "F<sup>#</sup>m7",
      "chord_10": "",
      "chord_11": "E/G<sup>#</sup>",
      "chord_12": "",
      "chord_13": "AM7",
      "chord_14": "",
      "chord_15": "",
      "chord_16": "E/G<sup>#</sup>",
      "lyrics_1": " -          나   를 부 -    르 고 -    있 - ",
      "lyrics_2": " -    어    -  -  -     -                       ",
      "lyrics_3": " -           아주 오랜 -    시 간 -    동 안",
      "lyrics_4": " -       -   -       -    -       -  -          ",
      "created_at": "2021-04-13 14:36:35"
    },
    {
      "id": 114454,
      "sort": 15,
      "chord_1": "F/A",
      "chord_2": "",
      "chord_3": "Bᵇ",
      "chord_4": "",
      "chord_5": "Csus4",
      "chord_6": "",
      "chord_7": "C",
      "chord_8": "",
      "chord_9": "(N.C)",
      "chord_10": "",
      "chord_11": "",
      "chord_12": "",
      "chord_13": "",
      "chord_14": "",
      "chord_15": "",
      "chord_16": "",
      "lyrics_1": " -           잊고 있던 -    목 소 - 리 에   ",
      "lyrics_2": " -",
      "lyrics_3": " -                      (물   결    을         ",
      "lyrics_4": " -           거슬 러    -      나 돌아 가   ",
      "created_at": "2021-04-13 14:36:35"
    },
    {
      "id": 114455,
      "sort": 16,
      "chord_1": "(N.C)",
      "chord_2": "",
      "chord_3": "",
      "chord_4": "C/E",
      "chord_5": "Dm7",
      "chord_6": "",
      "chord_7": "FM7/A",
      "chord_8": "",
      "chord_9": "Bᵇ6",
      "chord_10": "",
      "chord_11": "",
      "chord_12": "C13sus4",
      "chord_13": "F",
      "chord_14": "",
      "chord_15": "Csus4",
      "chord_16": "",
      "lyrics_1": " - )                                 내안에 바",
      "lyrics_2": " - 다    가 - 태    어 -    난 곳 - 으 로   ",
      "lyrics_3": " -                                   휩쓸 려   ",
      "lyrics_4": " -    길 을 잃어 도    -       자 유 로   와",
      "created_at": "2021-04-13 14:36:35"
    },
    {
      "id": 114456,
      "sort": 17,
      "chord_1": "BᵇM7",
      "chord_2": "",
      "chord_3": "",
      "chord_4": "C/E",
      "chord_5": "Dm7",
      "chord_6": "",
      "chord_7": "F/A",
      "chord_8": "",
      "chord_9": "Bᵇ",
      "chord_10": "",
      "chord_11": "",
      "chord_12": "C7",
      "chord_13": "F",
      "chord_14": "",
      "chord_15": "Csus4",
      "chord_16": "",
      "lyrics_1": " -                               더 이상 날가",
      "lyrics_2": " -    두 는 -    어 둠 -    에 눈 - 감 지 - ",
      "lyrics_3": " -                                   않         ",
      "lyrics_4": "아",
      "created_at": "2021-04-13 14:36:35"
    },
    {
      "id": 114457,
      "sort": 18,
      "chord_1": "Bᵇ",
      "chord_2": "",
      "chord_3": "",
      "chord_4": "C",
      "chord_5": "Dm7",
      "chord_6": "",
      "chord_7": "F/A",
      "chord_8": "",
      "chord_9": "BᵇM7",
      "chord_10": "",
      "chord_11": "",
      "chord_12": "Csus4",
      "chord_13": "F",
      "chord_14": "",
      "chord_15": "Csus4",
      "chord_16": "",
      "lyrics_1": " -",
      "lyrics_2": null,
      "lyrics_3": null,
      "lyrics_4": null,
      "created_at": "2021-04-13 14:36:35"
    },
    {
      "id": 114458,
      "sort": 19,
      "chord_1": "Bᵇ",
      "chord_2": "",
      "chord_3": "",
      "chord_4": "C",
      "chord_5": "Dm7",
      "chord_6": "",
      "chord_7": "F/A",
      "chord_8": "",
      "chord_9": "BᵇM7",
      "chord_10": "",
      "chord_11": "",
      "chord_12": "",
      "chord_13": "Eᵇ",
      "chord_14": "",
      "chord_15": "Bᵇ/D",
      "chord_16": "",
      "lyrics_1": null,
      "lyrics_2": null,
      "lyrics_3": " -                                            두",
      "lyrics_4": "번    다 시 -    날 모 -    른 척 - 하    지",
      "created_at": "2021-04-13 14:36:35"
    },
    {
      "id": 114459,
      "sort": 20,
      "chord_1": "Csus4",
      "chord_2": "",
      "chord_3": "",
      "chord_4": "",
      "chord_5": "F",
      "chord_6": "",
      "chord_7": "Csus4",
      "chord_8": "",
      "chord_9": "Bᵇ",
      "chord_10": "",
      "chord_11": "",
      "chord_12": "",
      "chord_13": "Dm7",
      "chord_14": "",
      "chord_15": "Am7",
      "chord_16": "F/A",
      "lyrics_1": " -                                   않   아   ",
      "lyrics_2": " -",
      "lyrics_3": " -                            우    우         ",
      "lyrics_4": " -                 -  -  -                 아 - ",
      "created_at": "2021-04-13 14:36:35"
    },
    {
      "id": 114460,
      "sort": 21,
      "chord_1": "Bᵇ",
      "chord_2": "",
      "chord_3": "",
      "chord_4": "",
      "chord_5": "F",
      "chord_6": "",
      "chord_7": "",
      "chord_8": "",
      "chord_9": "F",
      "chord_10": "",
      "chord_11": "C/E",
      "chord_12": "",
      "chord_13": "Bᵇ/D",
      "chord_14": "",
      "chord_15": "F/C",
      "chord_16": "",
      "lyrics_1": " -",
      "lyrics_2": " -                               그 럼에 도   ",
      "lyrics_3": " -                                   여전히 가",
      "lyrics_4": " -  - 끔 은 -                       삶에게 지",
      "created_at": "2021-04-13 14:36:35"
    },
    {
      "id": 114461,
      "sort": 22,
      "chord_1": "Bᵇ",
      "chord_2": "",
      "chord_3": "",
      "chord_4": "",
      "chord_5": "F",
      "chord_6": "",
      "chord_7": "",
      "chord_8": "",
      "chord_9": "Bᵇ/D",
      "chord_10": "",
      "chord_11": "C/E",
      "chord_12": "",
      "chord_13": "Fsus4",
      "chord_14": "F",
      "chord_15": "C/Bᵇ",
      "chord_16": "Bdim7",
      "lyrics_1": " -    는 날 - 들 도    -                 있 겠",
      "lyrics_2": " - 지                               또다 시   ",
      "lyrics_3": " -                   헤 매   일 지 - 라 도   ",
      "lyrics_4": " -                   돌 아   오 는 - 길 을   ",
      "created_at": "2021-04-13 14:36:35"
    },
    {
      "id": 114462,
      "sort": 23,
      "chord_1": "F/C",
      "chord_2": "",
      "chord_3": "Csus4",
      "chord_4": "",
      "chord_5": "(N.C)",
      "chord_6": "",
      "chord_7": "",
      "chord_8": "",
      "chord_9": "",
      "chord_10": "",
      "chord_11": "",
      "chord_12": "",
      "chord_13": "",
      "chord_14": "",
      "chord_15": "",
      "chord_16": "",
      "lyrics_1": " -           -       - - -                      ",
      "lyrics_2": " -                       알 아                 ",
      "lyrics_3": null,
      "lyrics_4": null,
      "created_at": "2021-04-13 14:36:35"
    }
  ]
}