{
  "info": {
    "id": 563,
    "title": "사노라면",
    "category": "한국 대중 음악",
    "sub_category": "록/메탈",
    "year": "1987",
    "month": "7",
    "time": "3:00",
    "beat": "4/4",
    "tempo": "57",
    "sec": "4.2",
    "original_key": "G",
    "singer": "전인권, 허성욱",
    "created_at": "2020-12-16 15:52:43"
  },
  "musics": [
    {
      "id": 13312,
      "sort": 1,
      "chord_1": "G",
      "chord_2": "",
      "chord_3": "",
      "chord_4": "",
      "chord_5": "",
      "chord_6": "",
      "chord_7": "",
      "chord_8": "",
      "chord_9": "",
      "chord_10": "",
      "chord_11": "",
      "chord_12": "",
      "chord_13": "G",
      "chord_14": "",
      "chord_15": "",
      "chord_16": "",
      "lyrics_1": " ",
      "lyrics_2": " ",
      "lyrics_3": "            사          노         라",
      "lyrics_4": "면",
      "created_at": "2020-12-16 15:52:43"
    },
    {
      "id": 13313,
      "sort": 2,
      "chord_1": "G",
      "chord_2": "",
      "chord_3": "",
      "chord_4": "",
      "chord_5": "",
      "chord_6": "",
      "chord_7": "",
      "chord_8": "",
      "chord_9": "",
      "chord_10": "",
      "chord_11": "",
      "chord_12": "",
      "chord_13": "E",
      "chord_14": "",
      "chord_15": "",
      "chord_16": "",
      "lyrics_1": " -          언          젠              가",
      "lyrics_2": "는",
      "lyrics_3": " -          밝          은          -",
      "lyrics_4": "날               도    오          겠",
      "created_at": "2020-12-16 15:52:43"
    },
    {
      "id": 13314,
      "sort": 3,
      "chord_1": "Am",
      "chord_2": "",
      "chord_3": "",
      "chord_4": "",
      "chord_5": "D",
      "chord_6": "",
      "chord_7": "",
      "chord_8": "",
      "chord_9": "G",
      "chord_10": "",
      "chord_11": "",
      "chord_12": "",
      "chord_13": "",
      "chord_14": "",
      "chord_15": "",
      "chord_16": "",
      "lyrics_1": "지",
      "lyrics_2": " -          흐          린         날",
      "lyrics_3": "도",
      "lyrics_4": " -          날          이              새",
      "created_at": "2020-12-16 15:52:43"
    },
    {
      "id": 13315,
      "sort": 4,
      "chord_1": "G",
      "chord_2": "",
      "chord_3": "",
      "chord_4": "",
      "chord_5": "C/G",
      "chord_6": "",
      "chord_7": "C",
      "chord_8": "",
      "chord_9": "D",
      "chord_10": "",
      "chord_11": "",
      "chord_12": "",
      "chord_13": "G",
      "chord_14": "",
      "chord_15": "",
      "chord_16": "",
      "lyrics_1": "면",
      "lyrics_2": "해          가         뜨          지",
      "lyrics_3": "않                      더          -                 ",
      "lyrics_4": "냐",
      "created_at": "2020-12-16 15:52:43"
    },
    {
      "id": 13316,
      "sort": 5,
      "chord_1": "G",
      "chord_2": "",
      "chord_3": "",
      "chord_4": "",
      "chord_5": "C",
      "chord_6": "",
      "chord_7": "",
      "chord_8": "",
      "chord_9": "",
      "chord_10": "",
      "chord_11": "",
      "chord_12": "",
      "chord_13": "G",
      "chord_14": "",
      "chord_15": "",
      "chord_16": "",
      "lyrics_1": null,
      "lyrics_2": "새               파    랗          게",
      "lyrics_3": "젊               다    는          게",
      "lyrics_4": "한               밑    천          인",
      "created_at": "2020-12-16 15:52:43"
    },
    {
      "id": 13317,
      "sort": 6,
      "chord_1": "G",
      "chord_2": "",
      "chord_3": "",
      "chord_4": "",
      "chord_5": "C",
      "chord_6": "",
      "chord_7": "",
      "chord_8": "",
      "chord_9": "",
      "chord_10": "",
      "chord_11": "",
      "chord_12": "",
      "chord_13": "A",
      "chord_14": "",
      "chord_15": "",
      "chord_16": "",
      "lyrics_1": "데",
      "lyrics_2": "째               째    하          게",
      "lyrics_3": "굴               지    말          고",
      "lyrics_4": "가                      슴         을            ",
      "created_at": "2020-12-16 15:52:43"
    },
    {
      "id": 13318,
      "sort": 7,
      "chord_1": "D",
      "chord_2": "",
      "chord_3": "",
      "chord_4": "",
      "chord_5": "G",
      "chord_6": "",
      "chord_7": "",
      "chord_8": "/F",
      "chord_9": "C",
      "chord_10": "",
      "chord_11": "",
      "chord_12": "",
      "chord_13": "D",
      "chord_14": "",
      "chord_15": "",
      "chord_16": "",
      "lyrics_1": "쫙                      펴         라",
      "lyrics_2": "내         일   은     해         가",
      "lyrics_3": "뜬                      다",
      "lyrics_4": "내         일   은     해         가",
      "created_at": "2020-12-16 15:52:43"
    },
    {
      "id": 13319,
      "sort": 8,
      "chord_1": "B7",
      "chord_2": "",
      "chord_3": "G",
      "chord_4": "",
      "chord_5": "",
      "chord_6": "",
      "chord_7": "",
      "chord_8": "",
      "chord_9": "G",
      "chord_10": "",
      "chord_11": "",
      "chord_12": "",
      "chord_13": "",
      "chord_14": "",
      "chord_15": "",
      "chord_16": "",
      "lyrics_1": "뜬                      다",
      "lyrics_2": " -          비          가         새",
      "lyrics_3": "는  \n -          비          가         새",
      "lyrics_4": " -          작          은              방\n는",
      "created_at": "2020-12-16 15:52:43"
    },
    {
      "id": 13320,
      "sort": 9,
      "chord_1": "G",
      "chord_2": "",
      "chord_3": "",
      "chord_4": "",
      "chord_5": "",
      "chord_6": "",
      "chord_7": "",
      "chord_8": "",
      "chord_9": "E",
      "chord_10": "",
      "chord_11": "",
      "chord_12": "",
      "chord_13": "Am",
      "chord_14": "",
      "chord_15": "",
      "chord_16": "",
      "lyrics_1": "에           \n -          작          은              방",
      "lyrics_2": " -          새          우          -\n에",
      "lyrics_3": "잠               을    잔          대\n잠               을    잔          대",
      "lyrics_4": "도\n도",
      "created_at": "2020-12-16 15:52:43"
    },
    {
      "id": 13321,
      "sort": 10,
      "chord_1": "D",
      "chord_2": "",
      "chord_3": "",
      "chord_4": "",
      "chord_5": "G",
      "chord_6": "",
      "chord_7": "",
      "chord_8": "",
      "chord_9": "",
      "chord_10": "",
      "chord_11": "",
      "chord_12": "",
      "chord_13": "G",
      "chord_14": "",
      "chord_15": "",
      "chord_16": "",
      "lyrics_1": " -          고          운          -",
      "lyrics_2": "님\n -          고          운          -",
      "lyrics_3": " -          함          께              라\n님",
      "lyrics_4": "면 \n -          함          께              라",
      "created_at": "2020-12-16 15:52:43"
    },
    {
      "id": 13322,
      "sort": 11,
      "chord_1": "C",
      "chord_2": "",
      "chord_3": "",
      "chord_4": "",
      "chord_5": "D",
      "chord_6": "",
      "chord_7": "",
      "chord_8": "",
      "chord_9": "G",
      "chord_10": "",
      "chord_11": "",
      "chord_12": "",
      "chord_13": "",
      "chord_14": "",
      "chord_15": "",
      "chord_16": "",
      "lyrics_1": "즐         거          웁          지\n면",
      "lyrics_2": "않                      더          -\n아                      -             ",
      "lyrics_3": "냐\n -",
      "lyrics_4": null,
      "created_at": "2020-12-16 15:52:43"
    },
    {
      "id": 13323,
      "sort": 12,
      "chord_1": "C",
      "chord_2": "",
      "chord_3": "",
      "chord_4": "",
      "chord_5": "",
      "chord_6": "",
      "chord_7": "",
      "chord_8": "",
      "chord_9": "G",
      "chord_10": "",
      "chord_11": "",
      "chord_12": "",
      "chord_13": "",
      "chord_14": "",
      "chord_15": "",
      "chord_16": "",
      "lyrics_1": "오               손    도          손",
      "lyrics_2": "속               삭    이          는",
      "lyrics_3": "밤               이    있          는",
      "lyrics_4": "한",
      "created_at": "2020-12-16 15:52:43"
    },
    {
      "id": 13324,
      "sort": 13,
      "chord_1": "C",
      "chord_2": "",
      "chord_3": "",
      "chord_4": "",
      "chord_5": "",
      "chord_6": "",
      "chord_7": "",
      "chord_8": "",
      "chord_9": "A",
      "chord_10": "",
      "chord_11": "",
      "chord_12": "",
      "chord_13": "D",
      "chord_14": "",
      "chord_15": "",
      "chord_16": "",
      "lyrics_1": "째               째    하          게",
      "lyrics_2": "굴               지    말          고",
      "lyrics_3": "가                      슴         을",
      "lyrics_4": "쫙                      펴         라",
      "created_at": "2020-12-16 15:52:43"
    },
    {
      "id": 13325,
      "sort": 14,
      "chord_1": "G",
      "chord_2": "",
      "chord_3": "",
      "chord_4": "",
      "chord_5": "C",
      "chord_6": "",
      "chord_7": "",
      "chord_8": "",
      "chord_9": "D",
      "chord_10": "",
      "chord_11": "",
      "chord_12": "",
      "chord_13": "B7",
      "chord_14": "",
      "chord_15": "G",
      "chord_16": "",
      "lyrics_1": "내         일   은     해         가",
      "lyrics_2": "뜬                      다",
      "lyrics_3": "내         일   은     해         가",
      "lyrics_4": "뜬                      다",
      "created_at": "2020-12-16 15:52:43"
    },
    {
      "id": 13326,
      "sort": 15,
      "chord_1": "G",
      "chord_2": "",
      "chord_3": "",
      "chord_4": "",
      "chord_5": "C",
      "chord_6": "",
      "chord_7": "",
      "chord_8": "",
      "chord_9": "D",
      "chord_10": "",
      "chord_11": "",
      "chord_12": "",
      "chord_13": "B7",
      "chord_14": "",
      "chord_15": "",
      "chord_16": "",
      "lyrics_1": "내         일   은     해         가",
      "lyrics_2": "뜬                      다",
      "lyrics_3": "내         일   은     해         가",
      "lyrics_4": "뜬",
      "created_at": "2020-12-16 15:52:43"
    },
    {
      "id": 13327,
      "sort": 16,
      "chord_1": "G",
      "chord_2": "",
      "chord_3": "",
      "chord_4": "",
      "chord_5": "G",
      "chord_6": "",
      "chord_7": "",
      "chord_8": "",
      "chord_9": "",
      "chord_10": "",
      "chord_11": "",
      "chord_12": "",
      "chord_13": "",
      "chord_14": "",
      "chord_15": "",
      "chord_16": "",
      "lyrics_1": "다",
      "lyrics_2": null,
      "lyrics_3": null,
      "lyrics_4": " -          사          노              라",
      "created_at": "2020-12-16 15:52:43"
    },
    {
      "id": 13328,
      "sort": 17,
      "chord_1": "G",
      "chord_2": "",
      "chord_3": "",
      "chord_4": "",
      "chord_5": "G",
      "chord_6": "",
      "chord_7": "",
      "chord_8": "",
      "chord_9": "",
      "chord_10": "",
      "chord_11": "",
      "chord_12": "",
      "chord_13": "",
      "chord_14": "",
      "chord_15": "",
      "chord_16": "",
      "lyrics_1": "면",
      "lyrics_2": " -          언          젠              가",
      "lyrics_3": "는",
      "lyrics_4": " -          밝          은          -",
      "created_at": "2020-12-16 15:52:43"
    },
    {
      "id": 13329,
      "sort": 18,
      "chord_1": "E",
      "chord_2": "",
      "chord_3": "",
      "chord_4": "",
      "chord_5": "Am",
      "chord_6": "",
      "chord_7": "",
      "chord_8": "",
      "chord_9": "D",
      "chord_10": "",
      "chord_11": "",
      "chord_12": "",
      "chord_13": "G",
      "chord_14": "",
      "chord_15": "",
      "chord_16": "",
      "lyrics_1": "날               도    오          겠",
      "lyrics_2": "지",
      "lyrics_3": " -          흐          린              날",
      "lyrics_4": "도",
      "created_at": "2020-12-16 15:52:43"
    },
    {
      "id": 13330,
      "sort": 19,
      "chord_1": "G",
      "chord_2": "",
      "chord_3": "",
      "chord_4": "",
      "chord_5": "G",
      "chord_6": "",
      "chord_7": "",
      "chord_8": "",
      "chord_9": "C",
      "chord_10": "",
      "chord_11": "",
      "chord_12": "",
      "chord_13": "D",
      "chord_14": "",
      "chord_15": "",
      "chord_16": "",
      "lyrics_1": " -          날          이              새",
      "lyrics_2": "면",
      "lyrics_3": "즐         거          웁          지",
      "lyrics_4": "않                      더          -",
      "created_at": "2020-12-16 15:52:43"
    },
    {
      "id": 13331,
      "sort": 20,
      "chord_1": "G",
      "chord_2": "",
      "chord_3": "",
      "chord_4": "",
      "chord_5": "G7",
      "chord_6": "",
      "chord_7": "",
      "chord_8": "",
      "chord_9": "C",
      "chord_10": "",
      "chord_11": "",
      "chord_12": "",
      "chord_13": "",
      "chord_14": "",
      "chord_15": "",
      "chord_16": "",
      "lyrics_1": "냐 ",
      "lyrics_2": " ",
      "lyrics_3": "새               파    랗          게",
      "lyrics_4": "젊               다    는          게",
      "created_at": "2020-12-16 15:52:43"
    },
    {
      "id": 13332,
      "sort": 21,
      "chord_1": "G",
      "chord_2": "",
      "chord_3": "",
      "chord_4": "",
      "chord_5": "",
      "chord_6": "",
      "chord_7": "",
      "chord_8": "",
      "chord_9": "C",
      "chord_10": "",
      "chord_11": "",
      "chord_12": "",
      "chord_13": "",
      "chord_14": "",
      "chord_15": "",
      "chord_16": "",
      "lyrics_1": "한               밑    천          인",
      "lyrics_2": "데",
      "lyrics_3": "째               째    하          게",
      "lyrics_4": "굴               지    말          고",
      "created_at": "2020-12-16 15:52:43"
    },
    {
      "id": 13333,
      "sort": 22,
      "chord_1": "A",
      "chord_2": "",
      "chord_3": "",
      "chord_4": "",
      "chord_5": "D",
      "chord_6": "",
      "chord_7": "",
      "chord_8": "",
      "chord_9": "G",
      "chord_10": "",
      "chord_11": "",
      "chord_12": "",
      "chord_13": "C",
      "chord_14": "",
      "chord_15": "",
      "chord_16": "",
      "lyrics_1": "가                      슴         을",
      "lyrics_2": "쫙                      펴         라",
      "lyrics_3": "내         일      은  해         가",
      "lyrics_4": "뜬                      다",
      "created_at": "2020-12-16 15:52:43"
    },
    {
      "id": 13334,
      "sort": 23,
      "chord_1": "D",
      "chord_2": "",
      "chord_3": "",
      "chord_4": "",
      "chord_5": "B7",
      "chord_6": "",
      "chord_7": "",
      "chord_8": "",
      "chord_9": "G",
      "chord_10": "",
      "chord_11": "",
      "chord_12": "",
      "chord_13": "",
      "chord_14": "",
      "chord_15": "",
      "chord_16": "",
      "lyrics_1": "내         일      은  해         가",
      "lyrics_2": "뜬",
      "lyrics_3": "다",
      "lyrics_4": null,
      "created_at": "2020-12-16 15:52:43"
    }
  ]
}