{
  "info": {
    "id": 5724,
    "title": "이 또한 지나가리라",
    "category": "한국 대중 음악",
    "sub_category": "발라드",
    "year": "2020",
    "month": "3",
    "time": "3:00",
    "beat": "12/8",
    "tempo": "59",
    "sec": "4.1",
    "original_key": "D♭",
    "singer": "신승훈",
    "created_at": "2021-05-05 15:03:20"
  },
  "musics": [
    {
      "id": 132583,
      "sort": 1,
      "chord_1": "Dᵇ",
      "chord_2": "",
      "chord_3": "",
      "chord_4": "",
      "chord_5": "GᵇM7",
      "chord_6": "",
      "chord_7": "",
      "chord_8": "",
      "chord_9": "Dᵇ",
      "chord_10": " ",
      "chord_11": "",
      "chord_12": "",
      "chord_13": "B",
      "chord_14": "",
      "chord_15": "",
      "chord_16": "",
      "lyrics_1": null,
      "lyrics_2": null,
      "lyrics_3": null,
      "lyrics_4": null,
      "created_at": "2021-05-05 15:03:20"
    },
    {
      "id": 132584,
      "sort": 2,
      "chord_1": "BM7",
      "chord_2": "",
      "chord_3": "",
      "chord_4": "",
      "chord_5": "Dᵇ",
      "chord_6": "",
      "chord_7": "Aᵇ/C",
      "chord_8": "",
      "chord_9": "Bᵇm7",
      "chord_10": "",
      "chord_11": "Dᵇ/Aᵇ",
      "chord_12": "",
      "chord_13": "Gᵇ",
      "chord_14": "",
      "chord_15": "Bᵇ7",
      "chord_16": "",
      "lyrics_1": "                                              너의",
      "lyrics_2": "하 루 가  기 나 긴  한 숨 같   아    그저",
      "lyrics_3": "떠 나 고  싶 은 거 - 니                 또",
      "lyrics_4": "기 대 하  고           휘 청 이  며",
      "created_at": "2021-05-05 15:03:20"
    },
    {
      "id": 132585,
      "sort": 3,
      "chord_1": "Eᵇm7",
      "chord_2": "",
      "chord_3": "Aᵇsus4",
      "chord_4": "Aᵇ7",
      "chord_5": "Dᵇ",
      "chord_6": "",
      "chord_7": "Aᵇ/C",
      "chord_8": "",
      "chord_9": "Bᵇm7",
      "chord_10": "",
      "chord_11": "DᵇM7/F",
      "chord_12": "",
      "chord_13": "Gᵇ",
      "chord_14": "",
      "chord_15": "Dᵇ/F",
      "chord_16": "",
      "lyrics_1": "버 티 고  있 는 거- 니",
      "lyrics_2": "때 로 는  세 상 이  봄 날 같   고",
      "lyrics_3": "때 로 는  안 개 만   자 욱 하- 지",
      "lyrics_4": "반 짝 였  다       어 두 워 졌  다",
      "created_at": "2021-05-05 15:03:20"
    },
    {
      "id": 132586,
      "sort": 4,
      "chord_1": "Eᵇm7",
      "chord_2": "",
      "chord_3": "Aᵇsus4",
      "chord_4": "Aᵇ7",
      "chord_5": "Gᵇ",
      "chord_6": "",
      "chord_7": "Dᵇ/F",
      "chord_8": "",
      "chord_9": "Aᵇsus4",
      "chord_10": "Aᵇ",
      "chord_11": "Aᵇsus2",
      "chord_12": "Aᵇ",
      "chord_13": "Gᵇ",
      "chord_14": "",
      "chord_15": "Dᵇ/F",
      "chord_16": "",
      "lyrics_1": "삶 이 란  그 런 거 - 야          가 야 할",
      "lyrics_2": "길          있     기- 에          헤 매 던",
      "lyrics_3": "날 - 들                              꽃 처 럼",
      "lyrics_4": "피          우          려 - 고    모 질 던",
      "created_at": "2021-05-05 15:03:20"
    },
    {
      "id": 132587,
      "sort": 5,
      "chord_1": "Aᵇsus4",
      "chord_2": "Aᵇ",
      "chord_3": "Aᵇsus2",
      "chord_4": "Aᵇ",
      "chord_5": "Gᵇ",
      "chord_6": "",
      "chord_7": "F7",
      "chord_8": "",
      "chord_9": "Bᵇm7",
      "chord_10": "",
      "chord_11": "Eᵇ7",
      "chord_12": "",
      "chord_13": "Eᵇm7",
      "chord_14": "",
      "chord_15": "Aᵇ7sus4",
      "chord_16": "",
      "lyrics_1": "바 - 람    ",
      "lyrics_2": "힘 내 란  말 은 하   지 않 을  게       이",
      "lyrics_3": "것 만 은  기 억 해- 줘                 거센",
      "lyrics_4": "강 물 처  럼      이  또 한 지  나 가-리",
      "created_at": "2021-05-05 15:03:20"
    },
    {
      "id": 132588,
      "sort": 6,
      "chord_1": "Dᵇ",
      "chord_2": "",
      "chord_3": "",
      "chord_4": "",
      "chord_5": "Gᵇ",
      "chord_6": "",
      "chord_7": "",
      "chord_8": "",
      "chord_9": "B",
      "chord_10": "",
      "chord_11": "",
      "chord_12": "",
      "chord_13": "Dᵇ",
      "chord_14": "",
      "chord_15": "Aᵇ/C",
      "chord_16": "",
      "lyrics_1": "라",
      "lyrics_2": null,
      "lyrics_3": " -                                           누군",
      "lyrics_4": "갈 위 해  박 수 만  치 는 내-  가    이젠",
      "created_at": "2021-05-05 15:03:20"
    },
    {
      "id": 132589,
      "sort": 7,
      "chord_1": "Bᵇm7",
      "chord_2": "",
      "chord_3": "Dᵇ/Aᵇ",
      "chord_4": "",
      "chord_5": "Gᵇ",
      "chord_6": "",
      "chord_7": "Bᵇ7",
      "chord_8": "",
      "chord_9": "Eᵇm7",
      "chord_10": "",
      "chord_11": "A7ᵇsus4",
      "chord_12": "Aᵇ7",
      "chord_13": "Dᵇ",
      "chord_14": "",
      "chord_15": "Aᵇ/C",
      "chord_16": "",
      "lyrics_1": "지 겨 워  지 진 않- 니                  가",
      "lyrics_2": "까 운 이  의       다 독 인 말  도",
      "lyrics_3": "들 리 지  않 는 거- 니",
      "lyrics_4": "그 치 지  않 는 비  는 없 잖   아",
      "created_at": "2021-05-05 15:03:20"
    },
    {
      "id": 132590,
      "sort": 8,
      "chord_1": "Bᵇm7",
      "chord_2": "",
      "chord_3": "DᵇM7/F",
      "chord_4": "",
      "chord_5": "Gᵇ",
      "chord_6": "",
      "chord_7": "Dᵇ/F",
      "chord_8": "",
      "chord_9": "Eᵇm7",
      "chord_10": "",
      "chord_11": "Aᵇsus4",
      "chord_12": "Aᵇ",
      "chord_13": "Gᵇ",
      "chord_14": "",
      "chord_15": "Dᵇ/F",
      "chord_16": "",
      "lyrics_1": "언 제 나  햇 살 일  순 없 잖 - 아",
      "lyrics_2": "부 딪 치  며       깨 달 아 가  는",
      "lyrics_3": "삶 이 란  그 런 거- 야           가 야 할",
      "lyrics_4": " 길         있     기- 에          헤 매 던",
      "created_at": "2021-05-05 15:03:20"
    },
    {
      "id": 132591,
      "sort": 9,
      "chord_1": "Aᵇsus4",
      "chord_2": "Aᵇ",
      "chord_3": "Aᵇsus4",
      "chord_4": "Aᵇ",
      "chord_5": "Gᵇ",
      "chord_6": "",
      "chord_7": "Dᵇ/F",
      "chord_8": "",
      "chord_9": "Aᵇsus4",
      "chord_10": "Aᵇ",
      "chord_11": "Aᵇsus2",
      "chord_12": "Aᵇ",
      "chord_13": "Gᵇ",
      "chord_14": "",
      "chord_15": "F7",
      "chord_16": "/A",
      "lyrics_1": "날 - 들                              꽃 처 럼",
      "lyrics_2": "피          우    려 - 고          모 질 던 ",
      "lyrics_3": "바-람",
      "lyrics_4": "힘 내 란  말 은 하   지 않 을  게      이",
      "created_at": "2021-05-05 15:03:20"
    },
    {
      "id": 132592,
      "sort": 10,
      "chord_1": "Bᵇm7",
      "chord_2": "/Aᵇ",
      "chord_3": "Eᵇ7",
      "chord_4": "",
      "chord_5": "Eᵇm7",
      "chord_6": "",
      "chord_7": "An7sus4",
      "chord_8": "",
      "chord_9": "B",
      "chord_10": "",
      "chord_11": "",
      "chord_12": "",
      "chord_13": "Dᵇ",
      "chord_14": "",
      "chord_15": "",
      "chord_16": "",
      "lyrics_1": "것 만 은  기 억 해- 줘                 거센",
      "lyrics_2": "강 물 처  럼      이  또 한 지  나 가-리",
      "lyrics_3": "라                       괜 찮 아  질 거 라",
      "lyrics_4": "위     로   -  하 는  게 아 냐   -",
      "created_at": "2021-05-05 15:03:20"
    },
    {
      "id": 132593,
      "sort": 11,
      "chord_1": "B",
      "chord_2": "",
      "chord_3": "",
      "chord_4": "",
      "chord_5": "Dᵇ",
      "chord_6": "",
      "chord_7": "Aᵇ/C",
      "chord_8": "",
      "chord_9": "Bᵇm7",
      "chord_10": "",
      "chord_11": "F7/A",
      "chord_12": "",
      "chord_13": "Aᵇm6",
      "chord_14": "",
      "chord_15": "Eᵇ/G",
      "chord_16": "",
      "lyrics_1": " -                  나도걸     어   -  온 길",
      "lyrics_2": "인 - 걸    -            거     친  -  세 상 ",
      "lyrics_3": "을 -        두 려 워  마           -  모 든",
      "lyrics_4": "사 랑 도   모 든 상  처  -  도      괜 찮",
      "created_at": "2021-05-05 15:03:20"
    },
    {
      "id": 132594,
      "sort": 12,
      "chord_1": "Eᵇm7",
      "chord_2": "",
      "chord_3": "Dᵇ/F",
      "chord_4": "",
      "chord_5": "Eᵇ/G",
      "chord_6": "",
      "chord_7": "",
      "chord_8": "",
      "chord_9": "Aᵇ7sus4",
      "chord_10": "",
      "chord_11": "A7sus4",
      "chord_12": "",
      "chord_13": "G",
      "chord_14": "",
      "chord_15": "D/F<sup>#</sup>",
      "chord_16": "",
      "lyrics_1": "아          너 를 더  찬 란 하   게      더",
      "lyrics_2": "너     답     게     만     들     테   -",
      "lyrics_3": "니- -        -                        누 군 갈",
      "lyrics_4": "사          랑     해- 서           빛 났 던",
      "created_at": "2021-05-05 15:03:20"
    },
    {
      "id": 132595,
      "sort": 13,
      "chord_1": "Asus4",
      "chord_2": "",
      "chord_3": "A",
      "chord_4": "",
      "chord_5": "G",
      "chord_6": "",
      "chord_7": "D/F<sup>#</sup>",
      "chord_8": "",
      "chord_9": "Asus4",
      "chord_10": "",
      "chord_11": "A",
      "chord_12": "",
      "chord_13": "G",
      "chord_14": "",
      "chord_15": "F<sup>#</sup>7",
      "chord_16": "",
      "lyrics_1": "날-들                                누 군 갈",
      "lyrics_2": "잊          기      위 해 - -      떠 나 온",
      "lyrics_3": "날-들 ",
      "lyrics_4": "아 픔 을  겪 어 야   시 작 되  는",
      "created_at": "2021-05-05 15:03:20"
    },
    {
      "id": 132596,
      "sort": 14,
      "chord_1": "Bm7",
      "chord_2": "/A",
      "chord_3": "E",
      "chord_4": "",
      "chord_5": "Em7",
      "chord_6": "",
      "chord_7": "A7sus4",
      "chord_8": "A",
      "chord_9": "Bm7",
      "chord_10": "",
      "chord_11": "E7",
      "chord_12": "",
      "chord_13": "Em7",
      "chord_14": "",
      "chord_15": "A7sus4",
      "chord_16": "",
      "lyrics_1": "순 간 이  있 다 는   걸                 지금",
      "lyrics_2": "아 프 다  면    너의 계 절 이  오 는 거",
      "lyrics_3": "야                                           거친",
      "lyrics_4": "바 람 은  그 렇 게   꽃  -  을   -  피 운",
      "created_at": "2021-05-05 15:03:20"
    },
    {
      "id": 132597,
      "sort": 15,
      "chord_1": "G",
      "chord_2": "",
      "chord_3": "D/F<sup>#</sup>",
      "chord_4": "",
      "chord_5": "Em7",
      "chord_6": "",
      "chord_7": "D/F<sup>#</sup>",
      "chord_8": "",
      "chord_9": "G",
      "chord_10": "",
      "chord_11": "D/F<sup>#</sup>",
      "chord_12": "",
      "chord_13": "C",
      "chord_14": "",
      "chord_15": "",
      "chord_16": "",
      "lyrics_1": "다",
      "lyrics_2": null,
      "lyrics_3": null,
      "lyrics_4": null,
      "created_at": "2021-05-05 15:03:20"
    },
    {
      "id": 132598,
      "sort": 16,
      "chord_1": "C",
      "chord_2": "",
      "chord_3": "",
      "chord_4": "",
      "chord_5": "",
      "chord_6": "",
      "chord_7": "",
      "chord_8": "",
      "chord_9": "",
      "chord_10": "",
      "chord_11": "",
      "chord_12": "",
      "chord_13": "",
      "chord_14": "",
      "chord_15": "",
      "chord_16": "",
      "lyrics_1": null,
      "lyrics_2": null,
      "lyrics_3": null,
      "lyrics_4": null,
      "created_at": "2021-05-05 15:03:20"
    }
  ]
}