{
  "info": {
    "id": 6836,
    "title": "Giant",
    "category": "한국 대중 음악",
    "sub_category": "록/메탈",
    "year": "2021",
    "month": "5",
    "time": "3:00",
    "beat": "4/4",
    "tempo": "74",
    "sec": "3.2",
    "original_key": "C#m",
    "singer": "우기 ((여자)아이들)",
    "created_at": "2021-06-08 23:50:34"
  },
  "musics": [
    {
      "id": 156540,
      "sort": 1,
      "chord_1": "F<sup>#</sup>m7",
      "chord_2": "",
      "chord_3": "",
      "chord_4": "",
      "chord_5": "C<sup>#</sup>m7",
      "chord_6": "",
      "chord_7": "",
      "chord_8": "",
      "chord_9": "E",
      "chord_10": "",
      "chord_11": "",
      "chord_12": "",
      "chord_13": "B",
      "chord_14": "",
      "chord_15": "",
      "chord_16": "",
      "lyrics_1": null,
      "lyrics_2": null,
      "lyrics_3": null,
      "lyrics_4": null,
      "created_at": "2021-06-08 23:50:34"
    },
    {
      "id": 156541,
      "sort": 2,
      "chord_1": "F<sup>#</sup>m7",
      "chord_2": "",
      "chord_3": "",
      "chord_4": "",
      "chord_5": "C<sup>#</sup>m7",
      "chord_6": "",
      "chord_7": "",
      "chord_8": "",
      "chord_9": "E",
      "chord_10": "",
      "chord_11": "",
      "chord_12": "",
      "chord_13": "B",
      "chord_14": "",
      "chord_15": "",
      "chord_16": "",
      "lyrics_1": "               I'm on the ropes now               ",
      "lyrics_2": " -        my arms are heav - y -  -               ",
      "lyrics_3": " -      Can't let them break me down -       ",
      "lyrics_4": " -         Don't let 'em push                       ",
      "created_at": "2021-06-08 23:50:34"
    },
    {
      "id": 156542,
      "sort": 3,
      "chord_1": "F<sup>#</sup>m7",
      "chord_2": "",
      "chord_3": "",
      "chord_4": "",
      "chord_5": "C<sup>#</sup>m7",
      "chord_6": "",
      "chord_7": "",
      "chord_8": "",
      "chord_9": "E",
      "chord_10": "",
      "chord_11": "",
      "chord_12": "",
      "chord_13": "B",
      "chord_14": "",
      "chord_15": "",
      "chord_16": "",
      "lyrics_1": " -             I hear the voic - es                   ",
      "lyrics_2": " -          say I'm not worth - y -  -              ",
      "lyrics_3": " -         No where to run but dig deep -      ",
      "lyrics_4": " -                        I won't be - a - fraid       ",
      "created_at": "2021-06-08 23:50:34"
    },
    {
      "id": 156543,
      "sort": 4,
      "chord_1": "F<sup>#</sup>m7",
      "chord_2": "",
      "chord_3": "",
      "chord_4": "",
      "chord_5": "C<sup>#</sup>m7",
      "chord_6": "",
      "chord_7": "",
      "chord_8": "",
      "chord_9": "E",
      "chord_10": "",
      "chord_11": "",
      "chord_12": "",
      "chord_13": "B",
      "chord_14": "",
      "chord_15": "(N.C)",
      "chord_16": "",
      "lyrics_1": "Hesitation got - me a-gainst the wall        ",
      "lyrics_2": "No more mistakes like I made before        ",
      "lyrics_3": "Cuz I know how - to win - this time -     ",
      "lyrics_4": " -                          I will rise up like a       ",
      "created_at": "2021-06-08 23:50:34"
    },
    {
      "id": 156544,
      "sort": 5,
      "chord_1": "F<sup>#</sup>m7",
      "chord_2": "",
      "chord_3": "",
      "chord_4": "",
      "chord_5": "C<sup>#</sup>m",
      "chord_6": "",
      "chord_7": "",
      "chord_8": "",
      "chord_9": "E",
      "chord_10": "",
      "chord_11": "",
      "chord_12": "",
      "chord_13": "B",
      "chord_14": "",
      "chord_15": "",
      "chord_16": "",
      "lyrics_1": "gi  -  ant            Hold my head a little       ",
      "lyrics_2": "high - er                        So don't you       ",
      "lyrics_3": "doubt me when I'm fighting my lonely nights",
      "lyrics_4": "                     ai - Standing tall-like a       ",
      "created_at": "2021-06-08 23:50:34"
    },
    {
      "id": 156545,
      "sort": 6,
      "chord_1": "F<sup>#</sup>m7",
      "chord_2": "",
      "chord_3": "",
      "chord_4": "",
      "chord_5": "C<sup>#</sup>m",
      "chord_6": "",
      "chord_7": "",
      "chord_8": "",
      "chord_9": "E",
      "chord_10": "",
      "chord_11": "",
      "chord_12": "",
      "chord_13": "B",
      "chord_14": "",
      "chord_15": "",
      "chord_16": "",
      "lyrics_1": "gi  -  ant                Yeah I'll be go-ing       ",
      "lyrics_2": "high - er                        So don't you       ",
      "lyrics_3": "doubt me when I'm down in my lonely fights",
      "lyrics_4": "                     ai - Stand up like a gi -       ",
      "created_at": "2021-06-08 23:50:34"
    },
    {
      "id": 156546,
      "sort": 7,
      "chord_1": "F<sup>#</sup>m",
      "chord_2": "",
      "chord_3": "",
      "chord_4": "",
      "chord_5": "C<sup>#</sup>m",
      "chord_6": "",
      "chord_7": "",
      "chord_8": "",
      "chord_9": "E",
      "chord_10": "",
      "chord_11": "",
      "chord_12": "",
      "chord_13": "B",
      "chord_14": "",
      "chord_15": "",
      "chord_16": "",
      "lyrics_1": "ant                            The scars in my     ",
      "lyrics_2": "heart Im - ma kiss you good - bye -  -       ",
      "lyrics_3": "can't bring me down you have no rights     ",
      "lyrics_4": "  to say I'm no better Feeding me lies -     ",
      "created_at": "2021-06-08 23:50:34"
    },
    {
      "id": 156547,
      "sort": 8,
      "chord_1": "F<sup>#</sup>m",
      "chord_2": "",
      "chord_3": "",
      "chord_4": "",
      "chord_5": "C<sup>#</sup>m7",
      "chord_6": "",
      "chord_7": "",
      "chord_8": "",
      "chord_9": "E",
      "chord_10": "",
      "chord_11": "",
      "chord_12": "",
      "chord_13": "B",
      "chord_14": "",
      "chord_15": "",
      "chord_16": "",
      "lyrics_1": " -  Leave it with your damn apologi-es       ",
      "lyrics_2": "Won't be needing your same excuse        ",
      "lyrics_3": "I can't be hurt    but I'm not a - fraid          ",
      "lyrics_4": "Not     -  a - fraid I won't be - a - fraid        ",
      "created_at": "2021-06-08 23:50:34"
    },
    {
      "id": 156548,
      "sort": 9,
      "chord_1": "F<sup>#</sup>m7",
      "chord_2": "",
      "chord_3": "",
      "chord_4": "",
      "chord_5": "C<sup>#</sup>m7",
      "chord_6": "",
      "chord_7": "",
      "chord_8": "",
      "chord_9": "E",
      "chord_10": "",
      "chord_11": "",
      "chord_12": "",
      "chord_13": "B",
      "chord_14": "",
      "chord_15": "(N.C)",
      "chord_16": "",
      "lyrics_1": "Hesitation got - me a-gainst the wall        ",
      "lyrics_2": "No more mistakes like I made before        ",
      "lyrics_3": "Cuz I know how - to win - this time -     ",
      "lyrics_4": " -                          I will rise up like a       ",
      "created_at": "2021-06-08 23:50:34"
    },
    {
      "id": 156549,
      "sort": 10,
      "chord_1": "F<sup>#</sup>m7",
      "chord_2": "",
      "chord_3": "",
      "chord_4": "",
      "chord_5": "C<sup>#</sup>m",
      "chord_6": "",
      "chord_7": "",
      "chord_8": "",
      "chord_9": "E",
      "chord_10": "",
      "chord_11": "",
      "chord_12": "",
      "chord_13": "B",
      "chord_14": "",
      "chord_15": "",
      "chord_16": "",
      "lyrics_1": "gi  -  ant            Hold my head a little       ",
      "lyrics_2": "high - er                        So don't you       ",
      "lyrics_3": "doubt me when I'm fighting my lonely nights",
      "lyrics_4": "                     ai - Standing tall-like a       ",
      "created_at": "2021-06-08 23:50:34"
    },
    {
      "id": 156550,
      "sort": 11,
      "chord_1": "F<sup>#</sup>m7",
      "chord_2": "",
      "chord_3": "",
      "chord_4": "",
      "chord_5": "C<sup>#</sup>m",
      "chord_6": "",
      "chord_7": "",
      "chord_8": "",
      "chord_9": "E",
      "chord_10": "",
      "chord_11": "",
      "chord_12": "",
      "chord_13": "B",
      "chord_14": "",
      "chord_15": "",
      "chord_16": "",
      "lyrics_1": "gi  -  ant                Yeah I'll be go-ing       ",
      "lyrics_2": "high - er                        So don't you       ",
      "lyrics_3": "doubt me when I'm down in my lonely fights",
      "lyrics_4": "                     ai - Stand up like a gi -       ",
      "created_at": "2021-06-08 23:50:34"
    },
    {
      "id": 156551,
      "sort": 12,
      "chord_1": "F<sup>#</sup>m",
      "chord_2": "",
      "chord_3": "",
      "chord_4": "",
      "chord_5": "C<sup>#</sup>m",
      "chord_6": "",
      "chord_7": "",
      "chord_8": "",
      "chord_9": "E",
      "chord_10": "",
      "chord_11": "",
      "chord_12": "",
      "chord_13": "B",
      "chord_14": "",
      "chord_15": "",
      "chord_16": "",
      "lyrics_1": "ant                      Stand up like a gi -       ",
      "lyrics_2": "ant -         -              I'll be go-ing my       ",
      "lyrics_3": "way - ay - eh yeah - ay - eh  e yeah -       ",
      "lyrics_4": " -                      Hold my head a little       ",
      "created_at": "2021-06-08 23:50:34"
    },
    {
      "id": 156552,
      "sort": 13,
      "chord_1": "F<sup>#</sup>m",
      "chord_2": "",
      "chord_3": "",
      "chord_4": "",
      "chord_5": "C<sup>#</sup>m",
      "chord_6": "",
      "chord_7": "",
      "chord_8": "",
      "chord_9": "E",
      "chord_10": "",
      "chord_11": "",
      "chord_12": "",
      "chord_13": "B",
      "chord_14": "",
      "chord_15": "(N.C)",
      "chord_16": "",
      "lyrics_1": "high - er             I'll be go-ing way up       ",
      "lyrics_2": "high - er                   I'll be go-ing my       ",
      "lyrics_3": "way - ay - eh yeah - ay - eh  e yeah -       ",
      "lyrics_4": " -                          I will rise up like a       ",
      "created_at": "2021-06-08 23:50:34"
    },
    {
      "id": 156553,
      "sort": 14,
      "chord_1": "F<sup>#</sup>m7",
      "chord_2": "",
      "chord_3": "",
      "chord_4": "",
      "chord_5": "C<sup>#</sup>m",
      "chord_6": "",
      "chord_7": "",
      "chord_8": "",
      "chord_9": "E",
      "chord_10": "",
      "chord_11": "",
      "chord_12": "",
      "chord_13": "B",
      "chord_14": "",
      "chord_15": "",
      "chord_16": "",
      "lyrics_1": "gi  -  ant            Hold my head a little       ",
      "lyrics_2": "high - er                        So don't you       ",
      "lyrics_3": "doubt me when I'm fighting my lonely nights",
      "lyrics_4": "                     ai - Standing tall-like a       ",
      "created_at": "2021-06-08 23:50:34"
    },
    {
      "id": 156554,
      "sort": 15,
      "chord_1": "F<sup>#</sup>m7",
      "chord_2": "",
      "chord_3": "",
      "chord_4": "",
      "chord_5": "C<sup>#</sup>m",
      "chord_6": "",
      "chord_7": "",
      "chord_8": "",
      "chord_9": "E",
      "chord_10": "",
      "chord_11": "",
      "chord_12": "",
      "chord_13": "B",
      "chord_14": "",
      "chord_15": "",
      "chord_16": "",
      "lyrics_1": "gi  -  ant                Yeah I'll be go-ing       ",
      "lyrics_2": "high - er                        So don't you       ",
      "lyrics_3": "doubt me when I'm down in my lonely fights",
      "lyrics_4": "                     ai - Stand up like a gi -       ",
      "created_at": "2021-06-08 23:50:34"
    },
    {
      "id": 156555,
      "sort": 16,
      "chord_1": "F<sup>#</sup>m",
      "chord_2": "",
      "chord_3": "",
      "chord_4": "",
      "chord_5": "C<sup>#</sup>m7",
      "chord_6": "",
      "chord_7": "",
      "chord_8": "",
      "chord_9": "E",
      "chord_10": "",
      "chord_11": "",
      "chord_12": "",
      "chord_13": "B",
      "chord_14": "",
      "chord_15": "",
      "chord_16": "",
      "lyrics_1": "ant                      Stand up like a gi -       ",
      "lyrics_2": "ant -         -                    So don't you      ",
      "lyrics_3": "doubt me when I'm down in my lonely fights",
      "lyrics_4": "                     ai -    -                              ",
      "created_at": "2021-06-08 23:50:34"
    }
  ]
}