{
  "info": {
    "id": 923,
    "title": " 달콤한 빈말 (Feat. 바버렛츠)",
    "category": "한국 대중 음악",
    "sub_category": "발라드",
    "year": "2017",
    "month": "5",
    "time": "3:00",
    "beat": "4/4",
    "tempo": "97",
    "sec": "2.5",
    "original_key": "E♭m-Em",
    "singer": "백아연",
    "created_at": "2021-01-05 22:10:55"
  },
  "musics": [
    {
      "id": 22461,
      "sort": 1,
      "chord_1": "Aᵇm9",
      "chord_2": "",
      "chord_3": "Dᵇ13sus4",
      "chord_4": "",
      "chord_5": "GᵇM13",
      "chord_6": "",
      "chord_7": "BM7",
      "chord_8": "",
      "chord_9": "Fm7(ᵇ5)",
      "chord_10": "",
      "chord_11": "Bᵇaug7",
      "chord_12": "",
      "chord_13": "EᵇM9",
      "chord_14": "",
      "chord_15": "",
      "chord_16": "",
      "lyrics_1": null,
      "lyrics_2": null,
      "lyrics_3": null,
      "lyrics_4": "                                                      조",
      "created_at": "2021-01-05 22:10:55"
    },
    {
      "id": 22462,
      "sort": 2,
      "chord_1": "Aᵇm9",
      "chord_2": "",
      "chord_3": "Dᵇ13sus4",
      "chord_4": "",
      "chord_5": "GᵇM13",
      "chord_6": "",
      "chord_7": "BM7",
      "chord_8": "",
      "chord_9": "Fm7(ᵇ5)",
      "chord_10": "",
      "chord_11": "Bᵇaug7",
      "chord_12": "",
      "chord_13": "EᵇM9",
      "chord_14": "",
      "chord_15": "",
      "chord_16": "",
      "lyrics_1": "만    간     얼    굴보  -     자           언",
      "lyrics_2": "제    밥     한    번먹  -    자             좋아",
      "lyrics_3": " -                     좋아  -                     난",
      "lyrics_4": "오    늘     도    기다  - 려                더",
      "created_at": "2021-01-05 22:10:55"
    },
    {
      "id": 22463,
      "sort": 3,
      "chord_1": "Aᵇm9",
      "chord_2": "",
      "chord_3": "Dᵇ13sus4",
      "chord_4": "",
      "chord_5": "GᵇM13",
      "chord_6": "",
      "chord_7": "BM7",
      "chord_8": "",
      "chord_9": "Fm7(ᵇ5)",
      "chord_10": "",
      "chord_11": "Bᵇaug7",
      "chord_12": "",
      "chord_13": "EᵇM9",
      "chord_14": "",
      "chord_15": "",
      "chord_16": "",
      "lyrics_1": "예    뻐     진    것같  -     네           뭐",
      "lyrics_2": "가    이     리    달콤 -     해              so",
      "lyrics_3": "sweet               so    sweet-              그",
      "lyrics_4": "럼    나     또    기대  - 해             빠라밤  ",
      "created_at": "2021-01-05 22:10:55"
    },
    {
      "id": 22464,
      "sort": 4,
      "chord_1": "Aᵇm9",
      "chord_2": "",
      "chord_3": "Dᵇ9sus4",
      "chord_4": "",
      "chord_5": "Gᵇ ",
      "chord_6": "",
      "chord_7": "BM7",
      "chord_8": "",
      "chord_9": "Fm7",
      "chord_10": "",
      "chord_11": "Bᵇaug7",
      "chord_12": "",
      "chord_13": "Eᵇm9",
      "chord_14": "",
      "chord_15": "",
      "chord_16": "",
      "lyrics_1": " -                  빠라밤  -                  빠라밥",
      "lyrics_2": "   빠라밥      빠라밤   -                     이",
      "lyrics_3": "번    에는 진심이맞    - 죠     거 짓말아니",
      "lyrics_4": " - 죠    진  짜보는거   - 죠             거짓말",
      "created_at": "2021-01-05 22:10:55"
    },
    {
      "id": 22465,
      "sort": 5,
      "chord_1": "Aᵇm9",
      "chord_2": "",
      "chord_3": "Dᵇ9sus4",
      "chord_4": "",
      "chord_5": "Gᵇ ",
      "chord_6": "",
      "chord_7": "BM7",
      "chord_8": "",
      "chord_9": "Fm7",
      "chord_10": "",
      "chord_11": "Bᵇaug7",
      "chord_12": "",
      "chord_13": "EᵇM9",
      "chord_14": "",
      "chord_15": "",
      "chord_16": "",
      "lyrics_1": " -                   이라도 -                  일단은",
      "lyrics_2": "   삼키고      볼래요   -                     맘  ",
      "lyrics_3": "이    썩    는    것      - 도                 아",
      "lyrics_4": "닌    데     뭐    어      - 때                빈",
      "created_at": "2021-01-05 22:10:55"
    },
    {
      "id": 22466,
      "sort": 6,
      "chord_1": "Am7",
      "chord_2": "",
      "chord_3": "F<sup>#</sup>7",
      "chord_4": "",
      "chord_5": "GM9",
      "chord_6": "",
      "chord_7": "CM13",
      "chord_8": "",
      "chord_9": "F<sup>#</sup>m7(ᵇ5)",
      "chord_10": "",
      "chord_11": "Baug7",
      "chord_12": "",
      "chord_13": "Dm7",
      "chord_14": "",
      "chord_15": "G7",
      "chord_16": "",
      "lyrics_1": "말    이     라    도난  - 좋아             빈",
      "lyrics_2": "말    이     라    도난   - 좋아            그 ",
      "lyrics_3": "말    한     마    디를   - 잡고            며",
      "lyrics_4": "칠    은     꿈    꿀수   - 있어            몇",
      "created_at": "2021-01-05 22:10:55"
    },
    {
      "id": 22467,
      "sort": 7,
      "chord_1": "CM7",
      "chord_2": "",
      "chord_3": "F<sup>#</sup>7",
      "chord_4": "",
      "chord_5": "Dm/F",
      "chord_6": "",
      "chord_7": "E7",
      "chord_8": "",
      "chord_9": "Am9",
      "chord_10": "",
      "chord_11": "Baug7",
      "chord_12": "",
      "chord_13": "EM9",
      "chord_14": "",
      "chord_15": "",
      "chord_16": "",
      "lyrics_1": "마    디     라    도난  - 좋아             몇    ",
      "lyrics_2": "마    디     라    도난   - 좋아            내    ",
      "lyrics_3": "하    룰     열    고     하    룰     닫    는    ",
      "lyrics_4": "말                   그      말 -",
      "created_at": "2021-01-05 22:10:55"
    },
    {
      "id": 22468,
      "sort": 8,
      "chord_1": "Am9 ",
      "chord_2": "",
      "chord_3": "F<sup>#</sup>7",
      "chord_4": "",
      "chord_5": "Dm/F",
      "chord_6": "",
      "chord_7": "E7",
      "chord_8": "",
      "chord_9": "Am9",
      "chord_10": "",
      "chord_11": "Baug7",
      "chord_12": "",
      "chord_13": "EM9",
      "chord_14": "",
      "chord_15": "",
      "chord_16": "",
      "lyrics_1": null,
      "lyrics_2": null,
      "lyrics_3": null,
      "lyrics_4": "                                                      담",
      "created_at": "2021-01-05 22:10:55"
    },
    {
      "id": 22469,
      "sort": 9,
      "chord_1": "Am9",
      "chord_2": "",
      "chord_3": "D9sus4",
      "chord_4": "",
      "chord_5": "GM7",
      "chord_6": "",
      "chord_7": "CM7",
      "chord_8": "",
      "chord_9": "F<sup>#</sup>m11",
      "chord_10": "",
      "chord_11": "Baug7",
      "chord_12": "",
      "chord_13": "EM9",
      "chord_14": "",
      "chord_15": "",
      "chord_16": "",
      "lyrics_1": "에    한     번    보자  -     고            말 ",
      "lyrics_2": "한    게     언    제인  -    지              몰라",
      "lyrics_3": "  -                    몰라  -                     난 ",
      "lyrics_4": "오    늘     도    기다   - 려                점",
      "created_at": "2021-01-05 22:10:55"
    },
    {
      "id": 22470,
      "sort": 10,
      "chord_1": "Am9",
      "chord_2": "",
      "chord_3": "D13sus4",
      "chord_4": "",
      "chord_5": "GM9",
      "chord_6": "",
      "chord_7": "CM13",
      "chord_8": "",
      "chord_9": "F<sup>#</sup>m11",
      "chord_10": "",
      "chord_11": "Baug7",
      "chord_12": "",
      "chord_13": "EM9",
      "chord_14": "",
      "chord_15": "",
      "chord_16": "",
      "lyrics_1": "점    더     예    뻐진  -    대             그 ",
      "lyrics_2": "말    만     열    두번  - 째                 싫어",
      "lyrics_3": "  -                    싫어  -                     저",
      "lyrics_4": "영    혼     없    는말   - 투             빠라밤",
      "created_at": "2021-01-05 22:10:55"
    },
    {
      "id": 22471,
      "sort": 11,
      "chord_1": "Am9",
      "chord_2": "",
      "chord_3": "D9sus4",
      "chord_4": "",
      "chord_5": "G",
      "chord_6": "",
      "chord_7": "CM7",
      "chord_8": "",
      "chord_9": "F<sup>#</sup>m7",
      "chord_10": "",
      "chord_11": "Baug7",
      "chord_12": "",
      "chord_13": "EM9",
      "chord_14": "",
      "chord_15": "",
      "chord_16": "",
      "lyrics_1": " -                  빠라밤  -                  빠라밥",
      "lyrics_2": "    빠라밥     빠라밤   -                     이",
      "lyrics_3": "번     에는 진심이맞   - 죠    거  짓말인거",
      "lyrics_4": " - 죠    이  젠안속아   - 요              달콤한",
      "created_at": "2021-01-05 22:10:55"
    },
    {
      "id": 22472,
      "sort": 12,
      "chord_1": "Am9",
      "chord_2": "",
      "chord_3": "D13sus4",
      "chord_4": "",
      "chord_5": "G",
      "chord_6": "",
      "chord_7": "CM13",
      "chord_8": "",
      "chord_9": "F<sup>#</sup>m7(ᵇ5)",
      "chord_10": "",
      "chord_11": "Baug7",
      "chord_12": "",
      "chord_13": "EM9",
      "chord_14": "",
      "chord_15": "",
      "chord_16": "",
      "lyrics_1": " -                  말들만  -                  삼키고",
      "lyrics_2": "    삼켰던     내맘이   -                     까",
      "lyrics_3": "맣     게    썩     어     - 가                는 ",
      "lyrics_4": "줄     도    모    르      - 고                빈",
      "created_at": "2021-01-05 22:10:55"
    },
    {
      "id": 22473,
      "sort": 13,
      "chord_1": "Am7",
      "chord_2": "",
      "chord_3": "F<sup>#</sup>7",
      "chord_4": "",
      "chord_5": "GM9",
      "chord_6": "",
      "chord_7": "CM13",
      "chord_8": "",
      "chord_9": "F<sup>#</sup>m7(ᵇ5)",
      "chord_10": "",
      "chord_11": "Baug7",
      "chord_12": "",
      "chord_13": "Dm7",
      "chord_14": "",
      "chord_15": "G7",
      "chord_16": "",
      "lyrics_1": "말    이     난    이젠  - 싫어             빈",
      "lyrics_2": "말    이     난    이제  - 싫어             그 ",
      "lyrics_3": "말     한    마     디를 - 잡고             밤",
      "lyrics_4": "새     헛    된    꿈꾸  - 게해             빈",
      "created_at": "2021-01-05 22:10:55"
    },
    {
      "id": 22474,
      "sort": 14,
      "chord_1": "CM7",
      "chord_2": "",
      "chord_3": "F<sup>#</sup>7",
      "chord_4": "",
      "chord_5": "Dm/F",
      "chord_6": "",
      "chord_7": "E7",
      "chord_8": "",
      "chord_9": "Am9",
      "chord_10": "",
      "chord_11": "Baug7",
      "chord_12": "",
      "chord_13": "EM9",
      "chord_14": "",
      "chord_15": "",
      "chord_16": "",
      "lyrics_1": "말    이     젠    정말 - 싫어             빈    ",
      "lyrics_2": "말    이     젠    정말  - 싫어             텅    ",
      "lyrics_3": "텅     빈    하    트     같    이     공    허    ",
      "lyrics_4": "한                   그      말 -",
      "created_at": "2021-01-05 22:10:55"
    },
    {
      "id": 22475,
      "sort": 15,
      "chord_1": "Am9",
      "chord_2": "",
      "chord_3": "D9sus4",
      "chord_4": "",
      "chord_5": "GM9",
      "chord_6": "",
      "chord_7": "E7sus4",
      "chord_8": "E7",
      "chord_9": "Am7",
      "chord_10": "",
      "chord_11": "Baug7",
      "chord_12": "",
      "chord_13": "E9sus4",
      "chord_14": "",
      "chord_15": "",
      "chord_16": "",
      "lyrics_1": " -              빈말    한 마    디로   -    하 ",
      "lyrics_2": "룰    버     티    던 -  나인    데  -",
      "lyrics_3": " -             어느    새  기    대가   -     커",
      "lyrics_4": "지    고커  - 져    서   -",
      "created_at": "2021-01-05 22:10:55"
    },
    {
      "id": 22476,
      "sort": 16,
      "chord_1": "Am7",
      "chord_2": "",
      "chord_3": "D9sus4",
      "chord_4": "",
      "chord_5": "E9sus4",
      "chord_6": "",
      "chord_7": "E/G<sup>#</sup>",
      "chord_8": "",
      "chord_9": "Am7",
      "chord_10": "",
      "chord_11": "",
      "chord_12": "",
      "chord_13": "B7",
      "chord_14": "",
      "chord_15": "",
      "chord_16": "",
      "lyrics_1": " -              툭툭    뱉 고    사라   - 진",
      "lyrics_2": "널    미     워    하     게된    건   -        내",
      "lyrics_3": "가변    한  - 걸     까  -          내  욕심이커",
      "lyrics_4": "져버    린  - 걸    까  -                     -",
      "created_at": "2021-01-05 22:10:55"
    },
    {
      "id": 22477,
      "sort": 17,
      "chord_1": "Baug7",
      "chord_2": "",
      "chord_3": "",
      "chord_4": "",
      "chord_5": "Am9",
      "chord_6": "",
      "chord_7": "F<sup>#</sup>7",
      "chord_8": "",
      "chord_9": "GM9",
      "chord_10": "",
      "chord_11": "CM7",
      "chord_12": "",
      "chord_13": "F<sup>#</sup>m7(ᵇ5)",
      "chord_14": "",
      "chord_15": "Baug7",
      "chord_16": "",
      "lyrics_1": " -                                                   빈",
      "lyrics_2": "말    이     난    이젠  - 싫어            빈",
      "lyrics_3": "말    이     난    이제  -싫어             그   ",
      "lyrics_4": "말    한     마     디를 - 잡고             밤",
      "created_at": "2021-01-05 22:10:55"
    },
    {
      "id": 22478,
      "sort": 18,
      "chord_1": "Dm7",
      "chord_2": "",
      "chord_3": "G7",
      "chord_4": "",
      "chord_5": "CM7",
      "chord_6": "",
      "chord_7": "F<sup>#</sup>7",
      "chord_8": "",
      "chord_9": "Dm/F",
      "chord_10": "",
      "chord_11": "E7",
      "chord_12": "",
      "chord_13": "Am9",
      "chord_14": "",
      "chord_15": "Baug7",
      "chord_16": "",
      "lyrics_1": "새    헛     된    꿈꾸  - 게해            빈",
      "lyrics_2": "말    이     젠    정말  - 싫어            빈    ",
      "lyrics_3": "말    이     젠    정말 - 싫어             텅",
      "lyrics_4": "텅    빈     하    트     같    이     공    허    ",
      "created_at": "2021-01-05 22:10:55"
    },
    {
      "id": 22479,
      "sort": 19,
      "chord_1": "EM9",
      "chord_2": "",
      "chord_3": "",
      "chord_4": "",
      "chord_5": "Am9",
      "chord_6": "",
      "chord_7": "F<sup>#</sup>7",
      "chord_8": "",
      "chord_9": "GM9",
      "chord_10": "",
      "chord_11": "CM13",
      "chord_12": "",
      "chord_13": "F<sup>#</sup>m7(ᵇ5)",
      "chord_14": "",
      "chord_15": "Baug7",
      "chord_16": "",
      "lyrics_1": "한                   그     말 -",
      "lyrics_2": null,
      "lyrics_3": null,
      "lyrics_4": null,
      "created_at": "2021-01-05 22:10:55"
    },
    {
      "id": 22480,
      "sort": 20,
      "chord_1": "Dm7",
      "chord_2": "",
      "chord_3": "G7",
      "chord_4": "",
      "chord_5": "CM7",
      "chord_6": "",
      "chord_7": "F<sup>#</sup>7",
      "chord_8": "",
      "chord_9": "Dm/F",
      "chord_10": "",
      "chord_11": "E7",
      "chord_12": "",
      "chord_13": "Am9",
      "chord_14": "",
      "chord_15": "Baug7",
      "chord_16": "",
      "lyrics_1": null,
      "lyrics_2": null,
      "lyrics_3": null,
      "lyrics_4": null,
      "created_at": "2021-01-05 22:10:55"
    },
    {
      "id": 22481,
      "sort": 21,
      "chord_1": "EM9",
      "chord_2": "",
      "chord_3": "",
      "chord_4": "",
      "chord_5": "",
      "chord_6": "",
      "chord_7": "",
      "chord_8": "",
      "chord_9": "",
      "chord_10": "",
      "chord_11": "",
      "chord_12": "",
      "chord_13": "",
      "chord_14": "",
      "chord_15": "",
      "chord_16": "",
      "lyrics_1": null,
      "lyrics_2": null,
      "lyrics_3": null,
      "lyrics_4": null,
      "created_at": "2021-01-05 22:10:55"
    }
  ]
}