{
  "info": {
    "id": 9595,
    "title": "그댄 달라요",
    "category": "한국 대중 음악",
    "sub_category": "발라드",
    "year": "2010",
    "month": "10",
    "time": "3:00",
    "beat": "4/4",
    "tempo": "84",
    "sec": "2.9",
    "original_key": "B♭",
    "singer": "버스커 버스커(Busker Busker)",
    "created_at": "2021-08-03 23:18:02"
  },
  "musics": [
    {
      "id": 220304,
      "sort": 1,
      "chord_1": "Gm",
      "chord_2": "",
      "chord_3": "Cm9",
      "chord_4": "",
      "chord_5": "Fsus4",
      "chord_6": "",
      "chord_7": "BᵇM7",
      "chord_8": "",
      "chord_9": "Gm",
      "chord_10": "",
      "chord_11": "Cm9",
      "chord_12": "",
      "chord_13": "Fsus4",
      "chord_14": "",
      "chord_15": "BᵇM7",
      "chord_16": "",
      "lyrics_1": null,
      "lyrics_2": null,
      "lyrics_3": null,
      "lyrics_4": null,
      "created_at": "2021-08-03 23:18:02"
    },
    {
      "id": 220305,
      "sort": 2,
      "chord_1": "Gm",
      "chord_2": "",
      "chord_3": "Cm9",
      "chord_4": "",
      "chord_5": "Fsus4",
      "chord_6": "",
      "chord_7": "BᵇM7",
      "chord_8": "",
      "chord_9": "Gm",
      "chord_10": "",
      "chord_11": "Cm9",
      "chord_12": "",
      "chord_13": "Fsus4",
      "chord_14": "",
      "chord_15": "BᵇM7",
      "chord_16": "",
      "lyrics_1": "비   교할  -    수없  -    는     사   랑",
      "lyrics_2": " -    이                  -",
      "lyrics_3": "비   교할  -    수없  -    는     설   렘",
      "lyrics_4": " -    바로  그   댄나  - 에게그  래요 -",
      "created_at": "2021-08-03 23:18:02"
    },
    {
      "id": 220306,
      "sort": 3,
      "chord_1": "Gm",
      "chord_2": "",
      "chord_3": "Cm9",
      "chord_4": "",
      "chord_5": "Fsus4",
      "chord_6": "",
      "chord_7": "BᵇM7",
      "chord_8": "",
      "chord_9": "Gm",
      "chord_10": "",
      "chord_11": "Cm9",
      "chord_12": "",
      "chord_13": "Fsus4",
      "chord_14": "",
      "chord_15": "BᵇM7",
      "chord_16": "",
      "lyrics_1": "      뭐    라   고말   - - 하려   - 해",
      "lyrics_2": "도      --   -    -       -",
      "lyrics_3": "      바    라   보다  -    가건   - 넨",
      "lyrics_4": "평 - 범한  - 인        사 - -      -",
      "created_at": "2021-08-03 23:18:02"
    },
    {
      "id": 220307,
      "sort": 4,
      "chord_1": "EᵇM7",
      "chord_2": "",
      "chord_3": "",
      "chord_4": "",
      "chord_5": "Fsus4",
      "chord_6": "",
      "chord_7": "",
      "chord_8": "",
      "chord_9": "Gm7",
      "chord_10": "",
      "chord_11": "",
      "chord_12": "",
      "chord_13": "BᵇM7",
      "chord_14": "",
      "chord_15": "",
      "chord_16": "",
      "lyrics_1": "      잊    을   수     없       -  이",
      "lyrics_2": "      날    바   뀌     게       -  한",
      "lyrics_3": "      아    직   은나     만 - 의 비밀",
      "lyrics_4": "       그   대   라는   - - 한사  - 람",
      "created_at": "2021-08-03 23:18:02"
    },
    {
      "id": 220308,
      "sort": 5,
      "chord_1": "EᵇM7",
      "chord_2": "",
      "chord_3": "",
      "chord_4": "",
      "chord_5": "Fsus4",
      "chord_6": "",
      "chord_7": "",
      "chord_8": "",
      "chord_9": "Gm7",
      "chord_10": "",
      "chord_11": "",
      "chord_12": "",
      "chord_13": "BᵇM7",
      "chord_14": "",
      "chord_15": "",
      "chord_16": "",
      "lyrics_1": "그대는너  무 - 달라  - 요                 내",
      "lyrics_2": "가본어느  눈 - 빛보  - 다              날",
      "lyrics_3": "기 - 대하  -    게해  -             언 젠 가",
      "lyrics_4": "날   너무  - 나        감   동시  - 킬    -",
      "created_at": "2021-08-03 23:18:02"
    },
    {
      "id": 220309,
      "sort": 6,
      "chord_1": "EᵇM7",
      "chord_2": "",
      "chord_3": "",
      "chord_4": "",
      "chord_5": "Fsus4",
      "chord_6": "",
      "chord_7": "",
      "chord_8": "",
      "chord_9": "Gm7",
      "chord_10": "",
      "chord_11": "",
      "chord_12": "",
      "chord_13": "BᵇM7",
      "chord_14": "",
      "chord_15": "",
      "chord_16": "",
      "lyrics_1": "것          같   은      -            고 백 이",
      "lyrics_2": "있   을것  - 같     -  아 -      ",
      "lyrics_3": "언          제   부     -    턴            가",
      "lyrics_4": "기      --   -    다려  -",
      "created_at": "2021-08-03 23:18:02"
    },
    {
      "id": 220310,
      "sort": 7,
      "chord_1": "EᵇM7",
      "chord_2": "",
      "chord_3": "",
      "chord_4": "",
      "chord_5": "Fsus4",
      "chord_6": "",
      "chord_7": "",
      "chord_8": "",
      "chord_9": "Gm7",
      "chord_10": "",
      "chord_11": "",
      "chord_12": "",
      "chord_13": "BᵇM7",
      "chord_14": "",
      "chord_15": "",
      "chord_16": "",
      "lyrics_1": "그대는너  무 - 빨라  - 요                날",
      "lyrics_2": "빠져들게  만 - 든시  - 간                 그",
      "lyrics_3": "댄   -      날   조     -    급     하   게",
      "lyrics_4": "만           - 들었죠  -",
      "created_at": "2021-08-03 23:18:02"
    },
    {
      "id": 220311,
      "sort": 8,
      "chord_1": "EᵇM7",
      "chord_2": "",
      "chord_3": "",
      "chord_4": "",
      "chord_5": "Fsus4",
      "chord_6": "",
      "chord_7": "",
      "chord_8": "",
      "chord_9": "Gm7",
      "chord_10": "",
      "chord_11": "",
      "chord_12": "",
      "chord_13": "BᵇM7",
      "chord_14": "",
      "chord_15": "",
      "chord_16": "",
      "lyrics_1": "한   걸음  - 만 - 더  -                     내",
      "lyrics_2": "게   다가  - 와 - 줘  -                     그",
      "lyrics_3": "댄   비    밀   일      -    수없  - 기    에",
      "lyrics_4": "  - - - -    -            -",
      "created_at": "2021-08-03 23:18:02"
    },
    {
      "id": 220312,
      "sort": 9,
      "chord_1": "EᵇM7",
      "chord_2": "",
      "chord_3": "",
      "chord_4": "",
      "chord_5": "Fsus4",
      "chord_6": "",
      "chord_7": "",
      "chord_8": "",
      "chord_9": "Gm7",
      "chord_10": "",
      "chord_11": "",
      "chord_12": "",
      "chord_13": "",
      "chord_14": "",
      "chord_15": "",
      "chord_16": "",
      "lyrics_1": null,
      "lyrics_2": null,
      "lyrics_3": null,
      "lyrics_4": null,
      "created_at": "2021-08-03 23:18:02"
    },
    {
      "id": 220313,
      "sort": 10,
      "chord_1": "Gm7",
      "chord_2": "",
      "chord_3": "Cm9",
      "chord_4": "",
      "chord_5": "Fsus4",
      "chord_6": "",
      "chord_7": "BᵇM7",
      "chord_8": "",
      "chord_9": "Gm7",
      "chord_10": "",
      "chord_11": "Cm9",
      "chord_12": "",
      "chord_13": "Fsus4",
      "chord_14": "",
      "chord_15": "BᵇM7",
      "chord_16": "",
      "lyrics_1": "비   교할  -    수없  -    는     슬   픔",
      "lyrics_2": " -    이                  -",
      "lyrics_3": "비   교할  -    수없  -    는     눈   물",
      "lyrics_4": " -    그대 나   를떠   - 나가는  상   상",
      "created_at": "2021-08-03 23:18:02"
    },
    {
      "id": 220314,
      "sort": 11,
      "chord_1": "Gm7",
      "chord_2": "",
      "chord_3": "Cm9",
      "chord_4": "",
      "chord_5": "Fsus4",
      "chord_6": "",
      "chord_7": "BᵇM7",
      "chord_8": "",
      "chord_9": "Gm7",
      "chord_10": "",
      "chord_11": "Cm9",
      "chord_12": "",
      "chord_13": "Fsus4",
      "chord_14": "",
      "chord_15": "BᵇM7",
      "chord_16": "",
      "lyrics_1": "      말    없   이떠   - - 나가   - 는",
      "lyrics_2": "너      --  -    -       -",
      "lyrics_3": "      잡    으   려잡  -    으려   - 고",
      "lyrics_4": "애 - 를써  - 봐        도 - -      -",
      "created_at": "2021-08-03 23:18:02"
    },
    {
      "id": 220315,
      "sort": 12,
      "chord_1": "EᵇM7",
      "chord_2": "",
      "chord_3": "",
      "chord_4": "",
      "chord_5": "Fsus4",
      "chord_6": "",
      "chord_7": "",
      "chord_8": "",
      "chord_9": "Gm7",
      "chord_10": "",
      "chord_11": "",
      "chord_12": "",
      "chord_13": "BᵇM7",
      "chord_14": "",
      "chord_15": "",
      "chord_16": "",
      "lyrics_1": "      멀    어   만     지       -  는",
      "lyrics_2": "       그   대   꿈     들       -  이",
      "lyrics_3": "      깨어 나   도힘  - 에     겨  - 운",
      "lyrics_4": "      그    대   라는   - - 한사   - 람",
      "created_at": "2021-08-03 23:18:02"
    },
    {
      "id": 220316,
      "sort": 13,
      "chord_1": "EᵇM7",
      "chord_2": "",
      "chord_3": "",
      "chord_4": "",
      "chord_5": "Fsus4",
      "chord_6": "",
      "chord_7": "",
      "chord_8": "",
      "chord_9": "Gm7",
      "chord_10": "",
      "chord_11": "",
      "chord_12": "",
      "chord_13": "BᵇM7",
      "chord_14": "",
      "chord_15": "",
      "chord_16": "",
      "lyrics_1": "그대는너  무 - 달라  - 요                내",
      "lyrics_2": "가본어느  눈 - 빛보  - 다                 날",
      "lyrics_3": "기   대하  -    게해   -            언 젠 가",
      "lyrics_4": "날   너무  - 나        감   동시  - 킬     -",
      "created_at": "2021-08-03 23:18:02"
    },
    {
      "id": 220317,
      "sort": 14,
      "chord_1": "EᵇM7",
      "chord_2": "",
      "chord_3": "",
      "chord_4": "",
      "chord_5": "Fsus4",
      "chord_6": "",
      "chord_7": "",
      "chord_8": "",
      "chord_9": "Gm7",
      "chord_10": "",
      "chord_11": "",
      "chord_12": "",
      "chord_13": "BᵇM7",
      "chord_14": "",
      "chord_15": "",
      "chord_16": "",
      "lyrics_1": "것          같   은                   고 백 이",
      "lyrics_2": "있   을것  - 같    -   아 -",
      "lyrics_3": "언          제   부      -    턴          가",
      "lyrics_4": "기          다           려       -  져",
      "created_at": "2021-08-03 23:18:02"
    },
    {
      "id": 220318,
      "sort": 15,
      "chord_1": "EᵇM7",
      "chord_2": "",
      "chord_3": "",
      "chord_4": "",
      "chord_5": "Fsus4",
      "chord_6": "",
      "chord_7": "",
      "chord_8": "",
      "chord_9": "Gm7",
      "chord_10": "",
      "chord_11": "",
      "chord_12": "",
      "chord_13": "BᵇM7",
      "chord_14": "",
      "chord_15": "",
      "chord_16": "",
      "lyrics_1": "그대는너  무 - 빨라  - 요                 날",
      "lyrics_2": "빠져들게  만 - 든시  - 간                 그",
      "lyrics_3": "댄   -      날   조      -    급    하   게",
      "lyrics_4": "만           - 들었죠  -",
      "created_at": "2021-08-03 23:18:02"
    },
    {
      "id": 220319,
      "sort": 16,
      "chord_1": "EᵇM7",
      "chord_2": "",
      "chord_3": "",
      "chord_4": "",
      "chord_5": "Fsus4",
      "chord_6": "",
      "chord_7": "",
      "chord_8": "",
      "chord_9": "Gm7",
      "chord_10": "",
      "chord_11": "",
      "chord_12": "",
      "chord_13": "BᵇM7",
      "chord_14": "",
      "chord_15": "",
      "chord_16": "",
      "lyrics_1": "한   걸음  - 만 - 더   -                    내",
      "lyrics_2": "게   다가  - 와 - 줘  -                     그",
      "lyrics_3": "댄   비    밀   일      -    수없  - 기    에",
      "lyrics_4": " -     - -   -            - 오     -  -",
      "created_at": "2021-08-03 23:18:02"
    },
    {
      "id": 220320,
      "sort": 17,
      "chord_1": "EᵇM7",
      "chord_2": "",
      "chord_3": "",
      "chord_4": "",
      "chord_5": "Fsus4",
      "chord_6": "",
      "chord_7": "",
      "chord_8": "",
      "chord_9": "Gm7",
      "chord_10": "",
      "chord_11": "",
      "chord_12": "",
      "chord_13": "BᵇM7",
      "chord_14": "",
      "chord_15": "",
      "chord_16": "",
      "lyrics_1": "오                        -            -",
      "lyrics_2": " -                         -            - 그대여",
      "lyrics_3": " -                         -                     그",
      "lyrics_4": "대   는    내   겐     너   무    달   라 -",
      "created_at": "2021-08-03 23:18:02"
    },
    {
      "id": 220321,
      "sort": 18,
      "chord_1": "EᵇM7",
      "chord_2": "",
      "chord_3": "",
      "chord_4": "",
      "chord_5": "Fsus4",
      "chord_6": "",
      "chord_7": "",
      "chord_8": "",
      "chord_9": "Gm7",
      "chord_10": "",
      "chord_11": "",
      "chord_12": "",
      "chord_13": "BᵇM7",
      "chord_14": "",
      "chord_15": "",
      "chord_16": "",
      "lyrics_1": "요                        -                 이",
      "lyrics_2": "젠                        -            -    내게",
      "lyrics_3": " -                         -                     그",
      "lyrics_4": "대   는    내   겐     너   무    달   라 -",
      "created_at": "2021-08-03 23:18:02"
    },
    {
      "id": 220322,
      "sort": 19,
      "chord_1": "Eᵇ",
      "chord_2": "",
      "chord_3": "",
      "chord_4": "",
      "chord_5": "Fsus4",
      "chord_6": "",
      "chord_7": "",
      "chord_8": "",
      "chord_9": "Gm7",
      "chord_10": "",
      "chord_11": "",
      "chord_12": "",
      "chord_13": "BᵇM7",
      "chord_14": "",
      "chord_15": "",
      "chord_16": "",
      "lyrics_1": null,
      "lyrics_2": null,
      "lyrics_3": null,
      "lyrics_4": null,
      "created_at": "2021-08-03 23:18:02"
    },
    {
      "id": 220323,
      "sort": 20,
      "chord_1": "EᵇM7",
      "chord_2": "",
      "chord_3": "",
      "chord_4": "",
      "chord_5": "Fsus4",
      "chord_6": "",
      "chord_7": "",
      "chord_8": "",
      "chord_9": "Gm7",
      "chord_10": "",
      "chord_11": "",
      "chord_12": "",
      "chord_13": "",
      "chord_14": "",
      "chord_15": "",
      "chord_16": "",
      "lyrics_1": null,
      "lyrics_2": null,
      "lyrics_3": null,
      "lyrics_4": null,
      "created_at": "2021-08-03 23:18:02"
    }
  ]
}